Workbook

Sheet Introduction
A18: Introduction: The assessment for Azure security establishes a unified framework of governance, identity, networking, data protection, and operational controls. It strategically aligns with international standards to enhance security maturity, minimize risks, ensure regulatory compliance, and enable secure cloud transformation while supporting business resilience and long-term operational scalability. ------------------------------------------------------------------------------------------------- Sections: 1. Network security - Secures and segments networks, controls traffic, prevents attacks, secures DNS and private connectivity for cloud. 2. Identity Management - Establishes secure identities, authentication, single sign-on, conditional access, managed identities and anomaly monitoring across environments. 3. Privileged Access - Protects administrative accounts and models, enforces least privilege, just-in-time access, privileged workstation controls, and oversight. 4. Data Protection - Discovers, classifies, encrypts, and monitors sensitive data; enforces keys, access controls, and data-loss prevention mechanisms. 5. Asset Management - Maintains inventory, tracks resources, governs service approvals, and enforces approved-service and application usage controls consistently. 6. Logging and Threat Detection - Collects, centralizes, retains logs; enables threat detection, high-quality alerts, SIEM integration, and investigative analytics capabilities. 7. Incident Response - Prepares for, detects, analyzes, contains, and recovers from incidents; automates response and conducts post-incident activities. 8. Posture and Vulnerability Management - Assesses configuration and vulnerabilities, tracks posture, performs scanning, prioritizes remediation, and automates corrective actions continuously. 9. Endpoint Security - Deploys EDR and anti-malware, secures endpoints, monitors behavior, and integrates endpoint telemetry into detection platforms. 10. Backup and Recovery - Ensures backups, validates restores, protects backup integrity, defines RPO/RTO, and supports disaster recovery planning activities. 11. DevOps Security - Integrates security into CI/CD, secures artifacts, enforces SAST/DAST, supply-chain checks, and pipeline hardening through automation. 12. Governance and Strategy - Defines security strategy, governance, roles, policies, multi-cloud strategy, and measurable compliance for sustained assurance oversight. ------------------------------------------------------------------------------------------------- Scope: TBD

Sheet Summary
A1: Sheet Names | B1: Total Controls | C1: Count of Compliant | D1: Count of Partial compliant | E1: Count of Non compliant | F1: Percentage | G1: Scale (out of 5)
A2: Network security | B2: =SUM('Network security'!M2:M100) | C2: =COUNTIF('Network security'!O:O,"Complete") | D2: =COUNTIF('Network security'!O:O,"Partial") | E2: =COUNTIF('Network security'!O:O,"Non-Compliant") | F2: =ROUND(IFERROR((((C2+0.5*D2)/(C2+D2+E2))*100),0), 1) | G2: =ROUND(IFERROR(((F2/100)*5),0), 1)
A3: Identity management | B3: =SUM('Identity management'!M2:M102) | C3: =COUNTIF('Identity management'!O:O,"Complete") | D3: =COUNTIF('Identity management'!O:O,"Partial") | E3: =COUNTIF('Identity management'!O:O,"Non-Compliant") | F3: =ROUND(IFERROR((((C3+0.5*D3)/(C3+D3+E3))*100),0), 1) | G3: =ROUND(IFERROR(((F3/100)*5),0), 1)
A4: Privileged access | B4: =SUM('Privileged access'!L2:L102) | C4: =COUNTIF('Privileged access'!N:N,"Complete") | D4: =COUNTIF('Privileged access'!N:N,"Partial") | E4: =COUNTIF('Privileged access'!N:N,"Non-Compliant") | F4: =ROUND(IFERROR((((C4+0.5*D4)/(C4+D4+E4))*100),0), 1) | G4: =ROUND(IFERROR(((F4/100)*5),0), 1)
A5: Data protection | B5: =SUM('Data protection'!M2:M103) | C5: =COUNTIF('Data protection'!O:O,"Complete") | D5: =COUNTIF('Data protection'!O:O,"Partial") | E5: =COUNTIF('Data protection'!O:O,"Non-Compliant") | F5: =ROUND(IFERROR((((C5+0.5*D5)/(C5+D5+E5))*100),0), 1) | G5: =ROUND(IFERROR(((F5/100)*5),0), 1)
A6: Asset management | B6: =SUM('Asset management'!L2:L100) | C6: =COUNTIF('Asset management'!N:N,"Complete") | D6: =COUNTIF('Asset management'!N:N,"Partial") | E6: =COUNTIF('Asset management'!N:N,"Non-Compliant") | F6: =ROUND(IFERROR((((C6+0.5*D6)/(C6+D6+E6))*100),0), 1) | G6: =ROUND(IFERROR(((F6/100)*5),0), 1)
A7: Logging and threat detection | B7: =SUM('Logging and threat detection'!M2:M105) | C7: =COUNTIF('Logging and threat detection'!O:O,"Complete") | D7: =COUNTIF('Logging and threat detection'!O:O,"Partial") | E7: =COUNTIF('Logging and threat detection'!O:O,"Non-Compliant") | F7: =ROUND(IFERROR((((C7+0.5*D7)/(C7+D7+E7))*100),0), 1) | G7: =ROUND(IFERROR(((F7/100)*5),0), 1)
A8: Incident response | B8: =SUM('Incident response'!L2:L106) | C8: =COUNTIF('Incident response'!N:N,"Complete") | D8: =COUNTIF('Incident response'!N:N,"Partial") | E8: =COUNTIF('Incident response'!N:N,"Non-Compliant") | F8: =ROUND(IFERROR((((C8+0.5*D8)/(C8+D8+E8))*100),0), 1) | G8: =ROUND(IFERROR(((F8/100)*5),0), 1)
A9: Posture and vulnerability manag | B9: =SUM('Posture and vulnerability manag'!M2:M107) | C9: =COUNTIF('Posture and vulnerability manag'!O:O,"Complete") | D9: =COUNTIF('Posture and vulnerability manag'!O:O,"Partial") | E9: =COUNTIF('Posture and vulnerability manag'!O:O,"Non-Compliant") | F9: =ROUND(IFERROR((((C9+0.5*D9)/(C9+D9+E9))*100),0), 1) | G9: =ROUND(IFERROR(((F9/100)*5),0), 1)
A10: Endpoint security | B10: =SUM('Endpoint security'!L2:L100) | C10: =COUNTIF('Endpoint security'!N:N,"Complete") | D10: =COUNTIF('Endpoint security'!N:N,"Partial") | E10: =COUNTIF('Endpoint security'!N:N,"Non-Compliant") | F10: =ROUND(IFERROR((((C10+0.5*D10)/(C10+D10+E10))*100),0), 1) | G10: =ROUND(IFERROR(((F10/100)*5),0), 1)
A11: Backup and recovery | B11: =SUM('Backup and recovery'!L2:L109) | C11: =COUNTIF('Backup and recovery'!N:N,"Complete") | D11: =COUNTIF('Backup and recovery'!N:N,"Partial") | E11: =COUNTIF('Backup and recovery'!N:N,"Non-Compliant") | F11: =ROUND(IFERROR((((C11+0.5*D11)/(C11+D11+E11))*100),0), 1) | G11: =ROUND(IFERROR(((F11/100)*5),0), 1)
A12: DevOps security | B12: =SUM('DevOps security'!L2:L100) | C12: =COUNTIF('DevOps security'!N:N,"Complete") | D12: =COUNTIF('DevOps security'!N:N,"Partial") | E12: =COUNTIF('DevOps security'!N:N,"Non-Compliant") | F12: =ROUND(IFERROR((((C12+0.5*D12)/(C12+D12+E12))*100),0), 1) | G12: =ROUND(IFERROR(((F12/100)*5),0), 1)
A13: Governance and strategy | B13: =SUM('Governance and strategy'!L2:L100) | C13: =COUNTIF('Governance and strategy'!N:N,"Complete") | D13: =COUNTIF('Governance and strategy'!N:N,"Partial") | E13: =COUNTIF('Governance and strategy'!N:N,"Non-Compliant") | F13: =ROUND(IFERROR((((C13+0.5*D13)/(C13+D13+E13))*100),0), 1) | G13: =ROUND(IFERROR(((F13/100)*5),0), 1)
A14: Total | B14: =SUM(B2:B13) | C14: =SUM(C2:C13) | D14: =SUM(D2:D13) | E14: =SUM(E2:E13) | F14: =ROUND(AVERAGE(F2:F13),1)

Sheet Azure Landing Questions
A1: Adoption Evaluation | B1: Options | C1: Response | D1: Score (1/1)
A2: How would you describe your cloud strategy? | B2: Developed as necessary, fragmented Clear and defined Transformational and innovative Requires optimization
A3: Are you responding to any critical business events, such as, datacenter exit, mergers and acquisition, end of support for mission-critical technologies, or response to regulatory compliance change? | B3: Yes No Don't know
A4: What are the critical business events driving your cloud transformation? | B4: Datacenter exit Merger, acquisition, or divestiture Reduction in capital expenses End of support for mission-critical technologies Response to regulatory compliance changes New data sovereignty requirements Reduction of disruptions and improvement of IT stability Report and manage the environmental impact of your business Expanding capacity without migrating because you're not able to move to OpEx or can't deprecate due to business needs
A5: Are there any other motivations that are driving your cloud transformation, other than those driven by critical business events? | B5: Cost savings Reduction in vendor or technical complexity Optimization of internal operations Increase in business agility Scaling to meet market and/or geographic demands Integration of a complex IT portfolio Improved customer experiences and engagements Transformation of products or services Market disruption with new products or services Preparation for, or building new, technical capabilities None of the above Democratization and/or self-service environments
A6: Has your cloud strategy been communicated broadly across the organization? | B6: Yes No, just at the leadership level We are in the process of communicating it Yes, but we need to reinforce the message Don't know
A7: Do you conduct regular cloud strategy reviews with the broader organization? | B7: Yes, consistently Yes, on an adhoc basis No
A8: Have you documented a cloud strategy with multi-year horizon and C-level participation and/or sponsorship? | B8: Yes, at least a 3-year plan Yes, but we haven't put it into action No, I would like to document a strategy
A9: What are the business outcomes driving your cloud transformation? | B9: Increase profitability while driving compliance Accelerate sales, improve customer lifetime value Acquire and retain customers, build a reputation Retain, recruit, and empower employees Meet market growth requirements and environmental sustainability metrics Global reach Performance and reliability None of the above
A10: Do these outcomes have associated business drivers, KPIs, and necessary technical capabilities? | B10: Yes No Don't know
A11: Have you developed a financial model or performed an economic assessment that provides business justification for moving to the cloud? | B11: Yes No Don't know
A12: It's important to understand how to account for cloud costs before you begin a cloud transformation journey. Select your company's model from the following common cloud accounting models. | B12: Cost-center model Profit-center model Charge-back model Showback or awareness-back model Don't know None of the above
A13: Do you understand how your resources need to scale depending on usage, utilization, and demand in a cloud context? | B13: Yes No
... A29: Answer | B29: Score Map
A30: Yes | B30: 1
A31: No | B31: 0
A32: 1 or more option | B32: 1

Sheet Setup-Questions
A1: Question | B1: Response Captured
A2: Do you currently use a CSPM or Defender for Cloud for continuous compliance and posture monitoring?
A3: Is there a SIEM/SOAR platform (like Microsoft Sentinel) collecting and correlating logs from all Azure resources?
A4: Do you have centralized identity management through Microsoft Entra ID with MFA and Conditional Access enforced
A5: Is Privileged Identity Management (PIM) or a similar solution in place for admin access control and elevation
A6: Are subscriptions and management groups organized under a governance model with defined policies and guardrails
A7: Is Azure Policy actively used to enforce configuration baselines and prevent non-compliant deployments?
A8: Are network controls such as firewalls, NSGs, and Private Endpoints configured to restrict external access?
A9: Is data encryption at rest and in transit enforced across all services using managed or customer-managed keys?
A10: Do you use Azure Key Vault or an HSM for secret and key management with access logging enabled?
A11: Are Defender for Servers/Containers/SQL or equivalent workload protections deployed and monitored?
A12: Do you perform vulnerability scanning and patch management for all compute, container, and PaaS workloads
A13: Is there an established incident response process integrated with alerting and automation (playbooks/runbooks)
... A21: Are regulatory and compliance dashboards (CIS, ISO, NIST, PCI, etc.) tracked and reported from Defender for Cloud or another tool

Sheet Network security
A1: Control ID | B1: Control Title | C1: Security Principle | D1: Azure Guidance | E1: MCSB Control ID Mapping | F1: CIS Mapping (v8) | G1: NIST SP 800-53 Mapping | H1: PCI-DSS Mapping (v3.2.1) | I1: CSA CCM Control ID | J1: IANS Azure Mapping | K1: Assessment Question | L1: Evidence to Collect | M1: Evidence Count | N1: Available Evidence Count | O1: Compliance Status | P1: Risk Severity (if non-compliant) | Q1: Implementation Gap | R1: Notes/Comments
A2: CSF-AZ-NS-01 | B2: Establish network segmentation boundaries | C2: Ensure that your virtual network deployment aligns to your enterprise segmentation strategy defined in the GS-2 security control. Any workload that could incur higher risk for the organization should be in isolated virtual networks. | D2: Create a virtual network (VNet) as a fundamental segmentation approach in your Azure network, so resources such as VMs can be deployed into the VNet within a network boundary. To further segment the network, you can create subnets inside VNet for smaller sub-networks. Use network security groups (NSG) as a network layer control to restrict or monitor traffic by port, protocol, source IP address, or destination IP address. Refer to NS-7: Simplify network security configuration to use Adaptive Network Hardening to recommend NSG hardening rules based on threat intelligence and traffic analysis result. You can also use application security groups (ASGs) to simplify complex configuration. Instead of defining policy based on explicit IP addresses in network security groups, ASGs enable you to configure network security as a natural extension of an application's structure, allowing you to group virtual machines and define network security policies based on those groups. | E2: NS-1 | F2: 3.12, 13.4, 4.4 | G2: AC-4, SC-2, SC-7 | H2: 1.1, 1.2, 1.3 | I2: IVS-03 | K2: 1. Are VNets and subnets defined for workload isolation? 2. Are NSGs applied to restrict/monitor traffic? 3. Are ASGs used for simplifying security rules? 4. Are segmentation rules aligned with enterprise segmentation strategy? | L2: 1. Azure VNet/subnet configuration export 2. NSG rule reports 3. ASG definitions 4. Network Hardening recommendations (Defender for Cloud or equivalent tool) 5. Architecture diagram showing segmentation boundaries | M2: 5 | N2: 0 | O2: Non-Compliant
A3: CSF-AZ-NS-02 | B3: Secure cloud native services with network controls | C3: Secure cloud services by establishing a private access point for resources. You should also disable or restrict access from public networks when possible. | D3: Deploy private endpoints for all Azure resources that support the Private Link feature to establish a private access point for the resources. Using Private Link will keep the private connection from routing through the public network. Note: Certain Azure services may also allow private communication through the service endpoint feature, though it is recommended to use Azure Private Link for secure and private access to services hosted on Azure platform. For certain services, you can choose to deploy VNet integration for the service where you can restrict the VNET to establish a private access point for the service. You also have the option to configure the service native network ACL rules or simply disable public network access to block access from public networks. For Azure VMs, unless there is a strong use case, you should avoid assigning public IPs/subnet directly to the VM interface and instead use gateway or load balancer services as the front-end for access by the public network. | E3: NS-2 | F3: 3.12, 4.4 | G3: AC-4, SC-2, SC-7 | H3: 1.1, 1.2, 1.3 | I3: IVS-06 | K3: 1. Are Azure PaaS services (e.g., Storage, SQL, Key Vault) integrated privately with VNets via Private Link or Service Endpoints? 2. Is public access disabled where feasible? 3. Are NSGs or firewall rules applied to restrict access to services? | L3: 1. Azure Private Link/Service Endpoint configuration 2. Firewall and NSG rule sets 3. Azure Policy assignments for restricting public access | M3: 3 | N3: 0 | O3: Partial
A4: CSF-AZ-NS-03 | B4: Deploy firewall at the edge of enterprise network | C4: Deploy a firewall to perform advanced filtering on network traffic to and from external networks. You can also use firewalls between internal segments to support a segmentation strategy. If required, use custom routes for your subnet to override the system route when you need to force the network traffic to go through a network appliance for security control purposes. | D4: Use Azure Firewall to provide fully stateful application layer traffic restriction (such as URL filtering) and/or central management over a large number of enterprise segments or spokes (in a hub/spoke topology). If you have a complex network topology, such as a hub/spoke setup, you may need to create user-defined routes (UDR) to ensure the traffic goes through the desired route. For example, you have the option to use an UDR to redirect egress internet traffic through a specific Azure Firewall or a network virtual appliance. | E4: NS-3 | F4: 4.4, 4.8, 13.10 | G4: AC-4, SC-7, CM-7 | H4: 1.1, 1.2, 1.3 | I4: IVS-08 | K4: 1. Is Azure Firewall deployed for centralized traffic control? 2. Are firewall policies defined with application and network rules? 3. Is Firewall Manager used for policy consistency? 4. Are threat intelligence-based filtering rules enabled? | L4: 1. Azure Firewall configuration and rules export 2. Firewall Manager policy assignments 3. Defender for Cloud recommendations | M4: 3 | N4: 0 | O4: Complete
A5: CSF-AZ-NS-04 | B5: Deploy intrusion detection/intrusion prevention systems (IDS/IPS) | C5: Use network intrusion detection and intrusion prevention systems (IDS/IPS) to inspect the network and payload traffic to or from your workload. Ensure that IDS/IPS is always tuned to provide high-quality alerts to your SIEM solution. | D5: Use Azure Firewall’s IDPS capabilities to protect your virtual network to alert on and/or block traffic to and from known malicious IP addresses and domains. For more in-depth host level detection and prevention capability, deploy host-based IDS/IPS or a host-based endpoint detection and response (EDR) solution, such as Microsoft Defender for Endpoint, at the VM level in conjunction with the network IDS/IPS. | E5: NS-4 | F5: 13.2, 13.3, 13.7, 13.8 | G5: SC-7, SI-4 | H5: 11.4 | I5: IVS-09 | K5: 1. Is IDS/IPS functionality enabled on Azure Firewall Premium or NVA appliances? 2. Is traffic being mirrored to an IDS solution (e.g., via Network Watcher TAP)? 3. Are alerts integrated with SIEM (Microsoft Sentinel)? | L5: 1. IDS/IPS configuration on Azure Firewall or NVAs 2. Logs showing intrusion detection alerts 3. Sentinel integration settings | M5: 3 | N5: 0 | O5: Complete
A6: CSF-AZ-NS-05 | B6: Deploy DDOS protection | C6: Deploy distributed denial of service (DDoS) protection to protect your network and applications from attacks. | D6: DDoS Protection Basic is automatically enabled to protect the Azure underlying platform infrastructure (e.g. Azure DNS) and requires no configuration from the users. For higher levels of protection of your application layer (Layer 7) attacks such as HTTP floods and DNS floods, enable the DDoS standard protection plan on your VNet to protect resources that are exposed to the public networks. | E6: NS-5 | F6: 13.1 | G6: SC-5, SC-7 | H6: 1.1, 1.2, 1.3, 6.6 | I6: IPY-09 | K6: 1. Is Azure DDoS Protection (Basic or Standard) enabled? 2. Are high-risk internet-facing VNets enrolled in DDoS Standard? 3. Are mitigation alerts integrated with monitoring? | L6: 1. DDoS Standard plan assignment in subscription 2. VNet DDoS protection configuration 3. Monitoring/alert logs from Defender for Cloud | M6: 3 | N6: 0 | O6: Partial
A7: CSF-AZ-NS-06 | B7: Deploy web application firewall | C7: Deploy a web application firewall (WAF) and configure the appropriate rules to protect your web applications and APIs from application-specific attacks. | D7: Use web application firewall (WAF) capabilities in Azure Application Gateway, Azure Front Door, and Azure Content Delivery Network (CDN) to protect your applications, services and APIs against application layer attacks at the edge of your network. Set your WAF in "detection" or "prevention mode", depending on your needs and threat landscape. Choose a built-in ruleset, such as OWASP Top 10 vulnerabilities, and tune it to your application needs. | E7: NS-6 | F7: 13.1 | G7: SC-7 | H7: 1.1, 1.2, 1.3 | I7: IVS-07 | K7: 1. Are Azure Application Gateway WAF or Azure Front Door WAF policies deployed? 2. Are managed rule sets enabled and customized as needed? 3. Are logs from WAF integrated into Sentinel? | L7: 1. WAF policy configuration export 2. Rule set assignment (OWASP CRS, custom rules) 3. Log Analytics/Sentinel WAF logs | M7: 3 | N7: 0 | O7: Non-Compliant
A8: CSF-AZ-NS-07 | B8: Simplify network security configuration | C8: When managing a complex network environment, use tools to simplify, centralize and enhance network security management. | D8: Use the following features to simplify the implementation and management of the virtual network, NSG rules, and Azure Firewall rules: 1. Use Azure Virtual Network Manager to group, configure, deploy, and manage virtual networks and NSG rules across regions and subscriptions. 2. Use Microsoft Defender for Cloud Adaptive Network Hardening to recommend NSG hardening rules that further limit ports, protocols and source IPs based on threat intelligence and traffic analysis result. 3. Use Azure Firewall Manager to centralize the firewall policy and route management of the virtual network. To simplify the firewall rules and network security groups implementation, you can also use the Azure Firewall Manager Azure Resource Manager(ARM) template. | E8: NS-7 | F8: 4.4, 4.8 | G8: AC-4, SC-2, SC-7 | H8: 1.1, 1.2, 1.3 | I8: IVS-04 | K8: 1. Is Adaptive Network Hardening enabled in Defender for Cloud? 2. Are NSGs being hardened using recommendations? 3. Is policy-as-code (Azure Policy/Blueprints) applied to enforce security rules? | L8: 1. Adaptive Network Hardening recommendations 2. Azure Policy assignment reports 3. Screenshots of NSG recommendation remediation | M8: 3 | N8: 0 | O8: Non-Compliant
A9: CSF-AZ-NS-08 | B9: Detect and disable insecure services and protocols | C9: Detect and disable insecure services and protocols at the OS, application, or software package layer. Deploy compensating controls if disabling insecure services and protocols are not possible. | D9: Use Microsoft Sentinel’s built-in Insecure Protocol Workbook to discover the use of insecure services and protocols such as SSL/TLSv1, SSHv1, SMBv1, LM/NTLMv1, wDigest, weak ciphers in Kerberos, and Unsigned LDAP Binds. Disable insecure services and protocols that do not meet the appropriate security standard. Note: If disabling insecure services or protocols is not possible, use compensating controls such as blocking access to the resources through network security group, Azure Firewall, or Azure Web Application Firewall to reduce the attack surface. | E9: NS-8 | F9: 4.4, 4.8 | G9: CM-2, CM-6, CM-7 | H9: 4.1, A2.1, A2.2, A2.3 | I9: LOG-03 | K9: 1. Are insecure protocols (e.g., SMBv1, Telnet, RDP over internet) blocked via NSGs or Firewall? 2. Are TLS 1.2+ enforced on services? 3. Are monitoring alerts enabled for deprecated/insecure services? | L9: 1. NSG/Firewall rules blocking insecure ports 2. Service configurations (TLS settings in App Gateway, SQL, Storage) 3. Defender for Cloud insecure protocol findings | M9: 3 | N9: 0 | O9: Partial
A10: CSF-AZ-NS-09 | B10: Connect on-premises or cloud network privately | C10: Use private connections for secure communication between different networks, such as cloud service provider datacenters and on-premises infrastructure in a colocation environment. | D10: For lightweight site-to-site or point-to-site connectivity, use Azure virtual private network (VPN) to create a secure connection between your on-premises site or end-user device and the Azure virtual network. For enterprise-level high performance connections, use Azure ExpressRoute (or Virtual WAN) to connect Azure datacenters and on-premises infrastructure in a co-location environment. When connecting two or more Azure virtual networks together, use virtual network peering. Network traffic between peered virtual networks is private and is kept on the Azure backbone network. | E10: NS-9 | F10: 12.7 | G10: CA-3, AC-17, AC-4 | H10: N/A | I10: LOG-2 | K10: 1. Is ExpressRoute or VPN Gateway used for hybrid connectivity? 2. Are Private Endpoints used for inter-service communication? 3. Is traffic encrypted over private connections? 4. Is forced tunneling configured if required? | L10: 1. ExpressRoute/VPN Gateway configuration 2. Private Link endpoint setup 3. Network architecture diagrams 4. Defender for Cloud hybrid network findings | M10: 4 | N10: 0 | O10: Complete
A11: CSF-AZ-NS-10 | B11: Ensure Domain Name System (DNS) security | C11: Ensure that Domain Name System (DNS) security configuration protects against known risks: 1. Use trusted authoritative and recursive DNS services across your cloud environment to ensure the client (such as operating systems and applications) receives the correct resolution result. 2. Separate the public and private DNS resolution so the DNS resolution process for the private network can be isolated from the public network. 3. Ensure your DNS security strategy also includes mitigations against common attacks, such as dangling DNS, DNS amplifications attacks, DNS poisoning and spoofing, and so on. | D11: Use Azure recursive DNS (usually assigned to your VM through DHCP or preconfigured in the service) or a trusted external DNS server in your workload recursive DNS setup, such as in the VM's operating system or in the application. Use Azure Private DNS for a private DNS zone setup where the DNS resolution process does not leave the virtual network. Use a custom DNS to restrict the DNS resolution to only allow trusted resolution to your client. Use Microsoft Defender for DNS for advanced protection against the following security threats to your workload or your DNS service: Data exfiltration from your Azure resources using DNS tunneling Malware communicating with a command-and-control server Communication with malicious domains, such as phishing and crypto mining DNS attacks in communication with malicious DNS resolvers You can also use Microsoft Defender for App Service to detect dangling DNS records if you decommission an App Service website without removing its custom domain from your DNS registrar. | E11: NS-10 | F11: 4.9, 9.2 | G11: SC-20, SC-21 | H11: N/A | I11: SEF-03 | K11: 1. Is Azure DNS with DNSSEC (where applicable) enabled? 2. Are private DNS zones used for internal name resolution? 3. Are outbound DNS queries filtered (Azure Firewall DNS proxy, custom resolver)? 4. Is SPF/DMARC/DKIM configured for domains? | L11: 1. Azure DNS zone configuration with DNSSEC status 2. Private DNS zone setup documentation 3. Firewall DNS proxy configuration 4. Domain security settings (SPF/DMARC/DKIM) | M11: 4 | N11: 0 | O11: Partial
A12: CSF-AZ-NS-11 | B12: Sensitive ports are not exposed to the internet | C12: Sensitive network ports are not exposed to the internet, including administrative ports (SSH/RDP), database ports and other common management ports. This is typically a good indicator that basic network security hygiene is in place, even if implemented manually. | D12: VMs or load balancers are not in network security groups that expose the following ports: - MongoDB ports 27017 and 27018 - FTP ports 20 or 21 - port 22 - port 3389 - Cassandra ports 7199 or 9160 or 8888 - Elasticsearch/Kibana ports 9200 or 9300 or 5601 - Kafka port 9092 - Memcached port 11211 - MySQL port 3306 - Oracle ports 1521 or 2483 - Postgres port 5432 - Redis port 6379 - Windows SQL Server ports 1433 or 1434 - Telnet port 23" | E12: N/A | F12: N/A | G12: N/A | H12: N/A | I12: N/A | J12: NET-02.1 | K12: Is the organization currently following the Azure Guidance ? | L12: Confirmation of the Assessment question | M12: 1 | O12: Non-Compliant
A13: CSF-AZ-NS-12 | B13: Security groups should not allow excessive port ranges | C13: Cloud networks should minimize potential attack paths by using tightly scoped security group rules, even on non-internet facing resources. One indicator of this is tightly scoped security groups applied to every compute resource that only allow a limited number of inbound ports (e.g., no more than five ports). | D13: Network Security Groups allow no more than five inbound ports Security groups are applied to all VMs/containers, not just subnets | E13: N/A | F13: N/A | G13: N/A | H13: N/A | I13: N/A | J13: NET-03.2 | K13: Is the organization currently following the Azure Guidance ? | L13: Confirmation of the Assessment question | M13: 1 | O13: Complete

Sheet Identity management
A1: Control ID | B1: Control Title | C1: Security Principle | D1: Azure Guidance | E1: MCSB Control ID Mapping | F1: CIS Mapping (v8) | G1: NIST SP 800-53 Mapping | H1: PCI-DSS Mapping (v3.2.1) | I1: CSA CCM Control ID | J1: IANS Azure Mapping | K1: Assessment Question | L1: Evidence to Collect | M1: Evidence Count | N1: Available Evidence Count | O1: Compliance Status | P1: Risk Severity (if non-compliant) | Q1: Implementation Gap | R1: Notes/Comments
A2: CSF-AZ-IM-01 | B2: Use centralized identity and authentication system | C2: Use a centralized identity and authentication system to govern your organization's identities and authentications for cloud and non-cloud resources. | D2: Azure Active Directory (Azure AD) is Azure's identity and authentication management service. You should standardize on Azure AD to govern your organization's identity and authentication in: Microsoft cloud resources, such as Azure Storage, Azure Virtual Machines (Linux and Windows), Azure Key Vault, PaaS, and SaaS applications. Your organization's resources, such as applications on Azure, third-party applications running on your corporate network resources, and third-party SaaS applications. Your enterprise identities in Active Directory by synchronization to Azure AD to ensure a consistent and centrally managed identity strategy. For the Azure services that apply, avoid use of local authentication methods and instead use Azure Active Directory to centralize your service authentications. | E2: IM-1 | F2: 6.7, 12.5 | G2: AC-2, AC-3, IA-2, IA-8 | H2: 7.2, 8.3 | I2: IAM-01, IAM-02, IAM-03 | K2: 1. Are all Azure resources (VMs, SQL, Storage, Key Vault, PaaS) integrated with Azure AD instead of local accounts? 2. Is on-premises Active Directory synchronized with Azure AD using AD Connect or SCIM? 3. Are third-party SaaS applications federated with Azure AD SSO (SAML/OIDC)? | L2: 1. Azure AD tenant configuration screenshot (Azure Portal → Azure Active Directory → Overview). 2. Export of Azure AD Connect sync rules (AD Connect → Synchronization Rules Editor). 3. List of Enterprise Applications integrated with SSO (AzureAD PowerShell: Get-AzureADServicePrincipal) | M2: 3 | O2: Partial
A3: CSF-AZ-IM-02 | B3: Protect identity and authentication systems | C3: Secure your identity and authentication system as a high priority in your organization's cloud security practice. Common security controls include: 1. Restrict privileged roles and accounts 2. Require strong authentication for all privileged access 3. Monitor and audit high risk activities | D3: Use the Azure AD security baseline and the Azure AD Identity Secure Score to evaluate your Azure AD identity security posture, and remediate security and configuration gaps. The Azure AD Identity Secure Score evaluates Azure AD for the following configurations: Use limited administrative roles Turn on user risk policy Designate more than one global admin Enable policy to block legacy authentication Ensure all users can complete multi-factor authentication for secure access Require MFA for administrative roles Enable self-service password reset Do not expire passwords Turn on sign-in risk policy Do not allow users to grant consent to unmanaged applications Use Azure AD Identity Protection to detect, investigate, and remediate identity-based risks. To similarly protect your on-premises Active Directory domain, use Defender for Identity. | E3: IM-2 | F3: 5.4, 6.5 | G3: AC-2, AC-3, IA-2, IA-8, SI-4 | H3: 8.2, 8.3 | I3: IAM-05, IAM-06, IVS-05 | K3: 1. Is Azure AD Identity Secure Score reviewed and tracked for remediation? 2. Are Identity Protection policies (user risk, sign-in risk) enabled? 3. Is Microsoft Defender for Identity deployed to monitor on-premises AD for lateral movement, credential theft, and Kerberos abuse? 4. Is logging enabled for privileged role assignments and admin consent to applications? | L3: 1. Azure AD Identity Secure Score export (Azure Portal → Security → Identity Secure Score → Export). 2. Conditional Access and Identity Protection policy export (AzureAD PowerShell: Get-AzureADMSConditionalAccessPolicy). 3. Defender for Identity sensor deployment status (Defender for Identity Portal → Configuration → Sensors). 4. Azure AD Audit logs for role assignments (AzureAD PowerShell: Get-AzureADAuditDirectoryLogs). | M3: 4 | O3: Complete
A4: CSF-AZ-IM-03 | B4: Manage application identities securely and automatically | C4: Use managed application identities instead of creating human accounts for applications to access resources and execute code. Managed application identities provide benefits such as reducing the exposure of credentials. Automate the rotation of credentials to ensure the security of the identities. | D4: Use Azure managed identities, which can authenticate to Azure services and resources that support Azure AD authentication. Managed identity credentials are fully managed, rotated, and protected by the platform, avoiding hard-coded credentials in source code or configuration files. For services that don't support managed identities, use Azure AD to create a service principal with restricted permissions at the resource level. It is recommended to configure service principals with certificate credentials and fall back to client secrets for authentication. | E4: IM-3: | F4: N/A | G4: AC-2, AC-3, IA-4, IA-5, IA-9 | H4: N/A | I4: IAM-07, IAM-08, IAM-09 | K4: 1. Are Managed Identities used for applications instead of hard-coded credentials? 2. For applications that require service principals, are certificate-based credentials enforced over client secrets? 3. Is credential rotation automated via Key Vault? 4. Are service principal permissions restricted to least privilege? | L4: 1. List of resources with Managed Identities enabled (Azure CLI: az resource list --query "[?identity!=null]"). 2. Service principal credential types (Azure CLI: az ad sp credential list --id <AppID>). 3. Key Vault secret rotation policy JSON export (az keyvault secret show --vault-name <vault> --name <secret>). 4. Role assignments of service principals (Azure CLI: az role assignment list --assignee <AppID>) | M4: 4 | O4: Complete
A5: CSF-AZ-IM-04 | B5: Authenticate server and services | C5: Authenticate remote servers and services from your client side to ensure you are connecting to trusted server and services. The most common server authentication protocol is Transport Layer Security (TLS), where the client-side (often a browser or client device) verifies the server by verifying the server’s certificate was issued by a trusted certificate authority. | D5: Many Azure services support TLS authentication by default. For services that don't support TLS authentication by default, or support disabling TLS, ensure it is always enabled to support the server/client authentication. Your client application should also be designed to verify server/client identity (by verifying the server’s certificate issued by a trusted certificate authority) in the handshake stage. | E5: IM-4 | F5: N/A | G5: IA-9 | H5: N/A | I5: IAM-10, IAM-11, IAM-12 | K5: 1. Is HTTPS/TLS enforced on all Azure services (Storage, App Services, Key Vault)? 2. Are certificates issued from trusted CAs and stored in Azure Key Vault/App Service Certificates? 3. Is mutual TLS (mTLS) configured where service-to-service trust is required? 4. Are legacy/unencrypted protocols disabled (FTP, LDAP without TLS, HTTP)? | L5: 1. Azure Policy compliance report for “HTTPS Only” (Azure Policy → Assignments →Effect: Deny). 2. Key Vault certificate inventory export (az keyvault certificate list --vault-name <vault>). 3. App Gateway / API Management TLS configuration JSON. 4. List of enabled protocols per Storage account (az storage account show --name <storage> --query "enableHttpsTrafficOnly"). | M5: 4 | O5: Non-Compliant
A6: CSF-AZ-IM-05 | B6: Use single sign-on (SSO) for application access | C6: Use single sign-on (SSO) to simplify the user experience for authenticating to resources including applications and data across cloud services and on-premises environments. | D6: Use Azure AD for workload application access (customer facing) access through Azure AD single sign-on (SSO), reducing the need for duplicate accounts. Azure AD provides identity and access management to Azure resources (in the management plane, including CLI, PowerShell, the portal), cloud applications, and on-premises applications. | E6: IM-5 | F6: 12.5 | G6: IA-4, IA-2, IA-8 | H6: N/A | I6: IAM-13, IAM-14 | K6: 1. Are enterprise SaaS applications federated with Azure AD using SAML or OIDC? 2. Are guest users accessing apps via Azure AD B2B configured with Conditional Access policies? 3. Are any applications still using standalone logins outside Azure AD federation? | L6: 1. Enterprise Application list (AzureAD PowerShell: Get-AzureADServicePrincipal | Select DisplayName, AppId). 2. Federation settings for B2B/B2C (Azure AD → External Identities → Cross-tenant access). 3. Conditional Access policy assignments for SaaS apps. 4. Sign-in logs showing federated vs non-federated authentication (Azure Portal → Azure AD → Sign-ins) | M6: 4 | O6: Partial
A7: CSF-AZ-IM-06 | B7: Use strong authentication controls | C7: Enforce strong authentication controls (strong passwordless authentication or multi-factor authentication) with your centralized identity and authentication management system for all access to resources. Authentication based on password credentials alone is considered legacy, as it is insecure and does not stand up to popular attack methods. When deploying strong authentication, configure administrators and privileged users first, to ensure the highest level of the strong authentication method, quickly followed by rolling out the appropriate strong authentication policy to all users. | D7: Azure AD supports strong authentication controls through passwordless methods and multi-factor authentication (MFA). Passwordless authentication: Use passwordless authentication as your default authentication method. There are three options available in passwordless authentication: Windows Hello for Business, Microsoft Authenticator app phone sign-in, and FIDO2 security keys. In addition, customers can use on-premises authentication methods such as smart cards. Multi-factor authentication: Azure MFA can be enforced on all users, select users, or at the per-user level based on sign-in conditions and risk factors. Enable Azure MFA and follow Microsoft Defender for Cloud identity and access management recommendations for your MFA setup. If legacy password-based authentication is still used for Azure AD authentication, be aware that cloud-only accounts (user accounts created directly in Azure) have a default baseline password policy. And hybrid accounts (user accounts that come from on-premises Active Directory) follow the on-premises password policies. For third-party applications and services that may have default IDs and passwords, you should disable or change them during initial service setup. | E7: IM-6 | F7: 6.3, 6.4 | G7: AC-2, AC-3, IA-2, IA-5, IA-8 | H7: 7.2, 8.2, 8.3, 8.4 | I7: IAM-15, IAM-16 | K7: 1. Is MFA enforced for all privileged accounts and end users via Conditional Access? 2. Are passwordless authentication methods (FIDO2, Authenticator app, Windows Hello) enabled? 3. Is Azure AD Password Protection in place with custom banned password lists? 4. Are break-glass accounts exempt from MFA but monitored with alerts? | L7: 1. Conditional Access policies export (Get-AzureADMSConditionalAccessPolicy). 2. MFA registration report (Azure AD → Security → MFA → Registration Details). 3. Azure AD Password Protection policy configuration (Azure AD → Security → Authentication Methods → Password Protection). 4. Azure Monitor alerts for break-glass account usage. | M7: 4 | O7: Partial
A8: CSF-AZ-IM-07 | B8: Restrict resource access based on conditions | C8: Explicitly validate trusted signals to allow or deny user access to resources, as part of a zero-trust access model. Signals to validate should include strong authentication of user account, behavioral analytics of user account, device trustworthiness, user or group membership, locations and so on. | D8: Use Azure AD conditional access for more granular access controls based on user-defined conditions, such as requiring user logins from certain IP ranges (or devices) to use MFA. Azure AD Conditional Access allows you to enforce access controls on your organization’s apps based on certain conditions. Define the applicable conditions and criteria for Azure AD conditional access in the workload. Consider the following common use cases: Requiring multi-factor authentication for users with administrative roles Requiring multi-factor authentication for Azure management tasks Blocking sign-ins for users attempting to use legacy authentication protocols Requiring trusted locations for Azure AD Multi-Factor Authentication registration Blocking or granting access from specific locations Blocking risky sign-in behaviors Requiring organization-managed devices for specific applications Note: Granular authentication session management controls can also be implemented through Azure AD conditional access policy, such as sign-in frequency and persistent browser session. | E8: IM-7 | F8: 3.3, 6.4, 13.5 | G8: AC-2, AC-3, AC-6 | H8: 7.2 | I8: IAM-04, IAM-17 | K8: 1. Are Conditional Access policies applied based on device compliance (Intune), location, or risk level? 2. Are session controls (sign-in frequency, persistent browser sessions) enforced? 3. Are Conditional Access policies tested against high-risk users and applications? | L8: 1. Full Conditional Access policy JSON export. 2. Intune compliance policy configuration export. 3. Azure AD sign-in logs showing risk-based MFA enforcement. 4. Conditional Access “What-If” test results (Azure Portal → Conditional Access → What If). | M8: 4 | O8: Complete
A9: CSF-AZ-IM-08 | B9: Restrict the exposure of credentials and secrets | C9: Ensure that application developers securely handle credentials and secrets: Avoid embedding the credentials and secrets into the code and configuration files Use key vault or a secure key store service to store the credentials and secrets Scan for credentials in source code. | D9: When using a managed identity is not an option, ensure that secrets and credentials are stored in secure locations such as Azure Key Vault, instead of embedding them into the code and configuration files. If you use Azure DevOps and GitHub for your code management platform: Implement Azure DevOps Credential Scanner to identify credentials within the code. For GitHub, use the native secret scanning feature to identify credentials or other form of secrets within the code. Clients such as Azure Functions, Azure Apps services, and VMs can use managed identities to access Azure Key Vault securely. See Data Protection controls related to the use of Azure Key Vault for secrets management. Note: Azure Key Vault provides automatic rotation for supported services. For secrets that cannot be automatically rotated, ensure they are manually rotated periodically and purged when no longer in use. | E9: IM-8 | F9: 16.9, 16.12 | G9: IA-5 | H9: 3.5, 6.3, 8.2 | I9: IAM-18, IVS-02 | K9: 1. Are all application secrets, keys, and certificates stored in Azure Key Vault? 2. Is RBAC enforced for Key Vault access instead of using access policies only? 3. Are DevOps pipelines scanned for secrets (e.g., GitHub secret scanning, Microsoft Security DevOps)? 4. Are rotation schedules in place for secrets/certificates? 5. Are audit logs enabled for Key Vault access events? | L9: 1. Key Vault access policy and RBAC role assignment export (az keyvault show --name <vault> and az role assignment list). 2. Key Vault diagnostic settings showing logs sent to Log Analytics/Event Hub. 3. Secret scanning reports from GitHub/Azure DevOps. 4. Secret and certificate expiry/rotation configuration (az keyvault certificate list --vault-name <vault>). | M9: 4 | O9: Non-Compliant
A10: CSF-AZ-IM-09 | B10: Secure user access to existing applications | C10: In a hybrid environment, where you have on-premises applications or non-native cloud applications using legacy authentication, consider solutions such as cloud access security broker (CASB), application proxy, single sign-on (SSO) to govern the access to these applications for the following benefits: Enforce a centralized strong authentication Monitor and control risky end-user activities Monitor and remediate risky legacy applications activities Detect and prevent sensitive data transmission | D10: Protect your on-premises and non-native cloud applications using legacy authentication by connecting them to: Azure AD Application Proxy and configure header-based authentication to allow single sign-on (SSO) access to the applications for remote users, while explicitly validating the trustworthiness of both remote users and devices with Azure AD Conditional Access. If required, use a a third-party Software-Defined Perimeter (SDP) solution which can offer similar functionality. Microsoft Defender for Cloud Apps, which serves a cloud access security broker (CASB) service to monitor and block user access to unapproved third-party SaaS applications. Your existing third-party application delivery controllers and networks. | E10: IM-9 | F10: 6.7, 12.5 | G10: AC-2, AC-3, SC-11 | H10: N/A | I10: EKM-01, EKM-02, IAM-19 | K10: 1. Are Azure AD sign-in and audit logs integrated into Sentinel or another SIEM? 2. Are risky sign-ins, leaked credentials, and impossible travel events monitored? 3. Are automated remediation actions applied (MFA challenge, block, conditional access)? 4. Are deprecated accounts or stale service principals detected and alerted on? | L10: 1. Azure AD sign-in logs export (az ad signin list or Portal → Azure AD → Sign-ins). 2. Sentinel analytics rules for identity anomalies (Azure Sentinel → Analytics → Rule templates). 3. Identity Protection risky users/sign-ins export. 4. Reports of inactive accounts (Get-AzureADUser -All $true | ?{$_.AccountEnabled -eq $false}) | M10: 4 | O10: Non-Compliant
A11: CSF-AZ-IM-10 | B11: SSO utilized for most console/portal access | C11: Access to the CSP's console/portal is done through consolidated single sign-on. This can be via an external SSO provider or one built into the cloud platform. | D11: This is the default for Azure, which requires the use of Entra ID (formerly Azure AD) | J11: IAM-02.1 | K11: Is the organization currently following the Azure Guidance ? | L11: Confirmation of the Assessment question | M11: 1 | O11: Complete
A12: CSF-AZ-IM-11 | B12: Users do not access the cloud console/portal outside of SSO | C12: Access to the cloud console or portal is only through the SSO portal, with the exception of a break-glass account (in case the SSO integration breaks). | D12: This is the default for Azure, which requires the use of Entra ID | J12: IAM-03.1 | K12: Is the organization currently following the Azure Guidance ? | L12: Confirmation of the Assessment question | M12: 1 | O12: Complete
A13: CSF-AZ-IM-12 | B13: An IAM data perimeter is enforced | C13: An IAM data perimeter as an advanced concept that restricts where API calls are able to originate. While it may be implemented in all environments, it is especially important for production accounts. This is typically based on IP address but may also rely on device restrictions. Each cloud provider enforces these differently (and not all cloud providers support the capability at all), but the goal is to prevent an attacker from stealing static or session credentials (including tokens) and using them from a location under that attackers control. | D13: The subscription uses conditional access policies consistently | J13: IAM-05.1 | K13: Is the organization currently following the Azure Guidance ? | L13: Confirmation of the Assessment question | M13: 1 | O13: Partial
A14: CSF-AZ-IM-13 | B14: JIT access used for access to production deployments | C14: Rather than allowing persistent human access to cloud deployments, a just-in-time (JIT) system provisions time-limited, session-based access on demand. JIT requests must meet policy guidelines and the system must support out-of-band approvals for highly privileged access. | D14: Azure PIM is enabled and used on all production subscriptions | J14: IAM-05.2 | K14: Is the organization currently following the Azure Guidance ? | L14: Confirmation of the Assessment question | M14: 1 | O14: Complete

Sheet Privileged access
A1: Control ID | B1: Control Title | C1: Security Principle | D1: Azure Guidance | E1: MCSB Control ID Mapping | F1: CIS Mapping (v8) | G1: NIST SP 800-53 Mapping | H1: PCI-DSS Mapping (v3.2.1) | I1: CSA CCM Control ID | J1: Assessment Question | K1: Evidence to Collect | L1: Evidence Count | M1: Available Evidence Count | N1: Compliance Status | O1: Risk Severity (if non-compliant) | P1: Implementation Gap | Q1: Notes/Comments
A2: CSF-AZ-PA-01 | B2: Separate and limit highly privileged/administrative users | C2: Ensure you identify all high business impact accounts. Limit the number of privileged/administrative accounts in your cloud's control plane, management plane and data/workload plane. | D2: You must secure all roles with direct or indirect administrative access to Azure hosted resources. Azure Active Directory (Azure AD) is Azure's default identity and access management service. The most critical built-in roles in Azure AD are Global Administrator and Privileged Role Administrator, because users assigned to these two roles can delegate administrator roles. With these privileges, users can directly or indirectly read and modify every resource in your Azure environment: Global Administrator / Company Administrator: Users with this role have access to all administrative features in Azure AD as well as services that use Azure AD identities. Privileged Role Administrator: Users with this role can manage role assignments in Azure AD, as well as within Azure AD Privileged Identity Management (PIM). In addition, this role allows management of all aspects of PIM and administrative units. Outside of Azure AD, Azure has built-in roles that can be critical for privileged access at the resource level. Owner: Grants full access to manage all resources, including the ability to assign roles in Azure RBAC. Contributor: Grants full access to manage all resources, but does not allow you to assign roles in Azure RBAC, manage assignments in Azure Blueprints, or share image galleries. User Access Administrator: Lets you manage user access to Azure resources. Note: You may have other critical roles that need to be governed if you use custom roles in the Azure AD level or resource level with certain privileged permissions assigned. In addition, users with the following three roles in Azure Enterprise Agreement (EA) portal should also be restricted as they can be used to directly or indirectly manage Azure subscriptions. Account Owner: Users with this role can manage subscriptions, including the creation and deletion of subscriptions. Enterprise Administrator: Users assigned with this role can manage (EA) portal users. Department Administrator: Users assigned with this role can change account owners within the department. Lastly, ensure that you also restrict privileged accounts in other management, identity, and security systems that have administrative access to your business-critical assets, such as Active Directory Domain Controllers (DCs), security tools, and system management tools with agents installed on business-critical systems. Attackers who compromise these management and security systems can immediately weaponize them to compromise business critical assets. | E2: PA-1 | F2: 5.4, 6.8 | G2: AC-2, AC-6 | H2: 7.1, 7.2, 8.1 | I2: IAM-10, IAM-11, IAM-12 | J2: 1. Are Global Administrator and Privileged Role Administrator accounts restricted and minimized? 2. Are resource-level privileged roles (Owner, User Access Administrator) tightly controlled? 3. Are EA portal roles (Account Owner, Enterprise Administrator, Department Administrator) limited to authorized personnel? 4. Are custom roles reviewed for privileged permissions? | K2: 1. Export of all Azure AD role assignments (az role assignment list --all). 2. List of Global Administrators and Privileged Role Administrators (Get-AzureADDirectoryRole). 3. Access review report for EA portal roles. 4. RBAC role assignment JSON for custom roles. | L2: 4
A3: CSF-AZ-PA-02 | B3: Avoid standing access for user accounts and permissions | C3: Instead of creating standing privileges, use just-in-time (JIT) mechanism to assign privileged access to the different resource tiers. | D3: Enable just-in-time (JIT) privileged access to Azure resources and Azure AD using Azure AD Privileged Identity Management (PIM). JIT is a model in which users receive temporary permissions to perform privileged tasks, which prevents malicious or unauthorized users from gaining access after the permissions have expired. Access is granted only when users need it. PIM can also generate security alerts when there is suspicious or unsafe activity in your Azure AD organization. | E3: PA-2 | F3: N/A | G3: AC-2 | H3: N/A | I3: IAM-13, IAM-14 | J3: 1. Is Just-In-Time (JIT) access configured via Azure AD Privileged Identity Management (PIM)? 2. Are privileged role activations requiring approval and MFA? 3. Is JIT VM access enabled for administrative ports (RDP/SSH) via Microsoft Defender for Cloud? | K3: 1. PIM configuration export (Get-AzureADMSPrivilegedRoleSetting). 2. Role activation logs from PIM. 3. Defender for Cloud JIT VM access configuration export._x000D_ | L3: 3
A4: CSF-AZ-PA-03 | B4: Manage lifecycle of identities and entitlements | C4: Use an automated process or technical control to manage the identity and access lifecycle including the request, review, approval, provision, and deprovision. | D4: Use Azure AD entitlement management features to automate access request workflows (for Azure resource groups). This enables workflows for Azure resource groups to manage access assignments, reviews, expiration, and dual or multi-stage approval. | E4: PA-3 | F4: 6.1, 6.2 | G4: AC-5, AC-6 | H4: 7.1, 7.2, 8.1 | I4: IVS-04, IVS-09 | J4: 1. Are access request workflows configured with Azure AD Entitlement Management? 2. Are expiration and approval workflows enforced for resource group and application access? 3. Are unused or excessive entitlements detected and remediated with Permissions Management? | K4: 1. Entitlement Management access package configuration (Azure Portal → Identity Governance). 2. Access review reports (Get-AzureADMSAccessReview). 3. Permissions Management report on unused entitlementsm | L4: 3
A5: CSF-AZ-PA-04 | B5: Review and reconcile user access regularly | C5: Conduct regular review of privileged account entitlements. Ensure the access granted to the accounts are valid for administration of control plane, management plane, and workloads. | D5: Review all privileged accounts and the access entitlements in Azure including Azure tenants, Azure services, VM/IaaS, CI/CD processes, and enterprise management and security tools. Use Azure AD access reviews to review Azure AD roles, Azure resource access roles, group memberships, and access to enterprise applications. Azure AD reporting can also provide logs to help discover stale accounts, or accounts which have not been used for certain amount of time. In addition, Azure AD Privileged Identity Management can be configured to alert when an excessive number of administrator accounts are created for a specific role, and to identify administrator accounts that are stale or improperly configured. | E5: PA-4 | F5: 5.1, 5.3, 5.5 | G5: AC-2, AC-6 | H5: 7.1, 7.2, 8.1, A3.4 | I5: LOG-01, LOG-03, LOG-07 | J5: 1. Are periodic access reviews performed for Azure AD roles, resource access, and application entitlements? 2. Are stale or inactive accounts flagged and removed? 3. Are alerts configured for sudden increases in privileged accounts? | K5: 1. Azure AD Access Review reports. 2. Audit logs of account removal actions. 3. PIM configuration for admin count threshold alerts | L5: 3
A6: CSF-AZ-PA-05 | B6: Set up emergency access | C6: Set up emergency access to ensure that you are not accidentally locked out of your critical cloud infrastructure (such as your identity and access management system) in an emergency. Emergency access accounts should be rarely used and can be highly damaging to the organization if compromised, but their availability to the organization is also critically important for the few scenarios when they are required. | D6: To prevent being accidentally locked out of your Azure AD organization, set up an emergency access account (e.g., an account with Global Administrator role) for access when normal administrative accounts cannot be used. Emergency access accounts are usually highly privileged, and they should not be assigned to specific individuals. Emergency access accounts are limited to emergency or "break glass" scenarios where normal administrative accounts can't be used. You should ensure that the credentials (such as password, certificate, or smart card) for emergency access accounts are kept secure and known only to individuals who are authorized to use them only in an emergency. You may also use additional controls, such dual controls (e.g., splitting the credential into two pieces and giving it to separate persons) to enhance the security of this process. You should also monitor the sign-in and audit logs to ensure that emergency access accounts are only used when authorized. | E6: PA-5 | F6: N/A | G6: AC-2 | H6: N/A | I6: IAM-05, IAM-06, CCC-03 | J6: 1. Are at least two emergency access (break-glass) accounts created with Global Administrator role? 2. Are credentials stored securely (HSM, offline vault, split control)? 3. Are emergency account sign-ins monitored and alerted? 4. Are MFA exclusions documented only for break-glass accounts? | K6: 1. List of emergency accounts and their assigned roles. 2. Credential storage method documentation (Key Vault, password vault). 3. Azure AD sign-in logs filtered for emergency accounts. 4. Alert configuration for break-glass usage | L6: 4
A7: CSF-AZ-PA-06 | B7: Use privileged access workstations | C7: Secured, isolated workstations are critically important for the security of sensitive roles like administrator, developer, and critical service operator. | D7: Use Azure Active Directory, Microsoft Defender, and/or Microsoft Intune to deploy privileged access workstations (PAW) on-premises or in Azure for privileged tasks. The PAW should be centrally managed to enforce secured configuration, including strong authentication, software and hardware baselines, and restricted logical and network access. You may also use Azure Bastion which is a fully platform-managed PaaS service that can be provisioned inside your virtual network. Azure Bastion allows RDP/SSH connectivity to your virtual machines directly from the Azure portal using a web browser. | E7: PA-6 | F7: 12.8, 13.5 | G7: AC-2, SC-2, SC-7 | H7: N/A | I7: IAM-17, SEF-03 | J7: 1. Are privileged access workstations (PAW) deployed and managed via Intune or GPO? 2. Are PAWs restricted with conditional access policies (device compliance required)? 3. Is Azure Bastion used for secure VM administration instead of direct RDP/SSH exposure? | K7: 1. Intune device compliance policy reports for PAWs. 2. Conditional Access policies requiring compliant devices. 3. Bastion deployment configuration. | L7: 3
A8: CSF-AZ-PA-07 | B8: Follow just enough administration (least privilege) principle | C8: Follow the just enough administration (least privilege) principle to manage permissions at fine-grained level. Use features such as role-based access control (RBAC) to manage resource access through role assignments. | D8: Use Azure role-based access control (Azure RBAC) to manage Azure resource access through role assignments. Through RBAC, you can assign roles to users, groups, service principals, and managed identities. There are pre-defined built-in roles for certain resources, and these roles can be inventoried or queried through tools such as Azure CLI, Azure PowerShell, and the Azure portal. The privileges you assign to resources through Azure RBAC should always be limited to what's required by the roles. Limited privileges will complement the just-in-time (JIT) approach of Azure AD Privileged Identity Management (PIM), and those privileges should be reviewed periodically. If required, you can also use PIM to define a time-bound assignment, which is a condition in a role assignment where a user can only activate the role within the specified start and end dates. | E8: PA-7 | F8: 3.3, 6.8 | G8: AC-2, AC-3, AC-6 | H8: 7.1, 7.2 | I8: IAM-15, IAM-16 | J8: 1. Are privileged operations (role assignments, admin consent to apps, directory configuration changes) logged? 2. Are alerts generated for high-risk operations (e.g., new Global Admin creation)? 3. Are logs integrated with SIEM (Microsoft Sentinel)? | K8: 1. Azure AD Audit logs export for privileged actions. 2. Sentinel analytics rule definitions for privileged operations. 3. Alert history showing privileged changes._x000D_ | L8: 3
A9: CSF-AZ-PA-08 | B9: Determine access process for cloud provider support | C9: Establish an approval process and access path for requesting and approving vendor support requests and temporary access to your data through a secure channel. | D9: In support scenarios where Microsoft needs to access your data, use Customer Lockbox to review and either approve or reject each data access request made by Microsoft. | E9: PA-8 | F9: 6.1, 6.2 | G9: AC-4, AC-2, AC-3 | H9: N/A | I9: IPY-04, SEF-02, SEF-03 | J9: 1. Is Customer Lockbox enabled for Microsoft support access requests? 2. Are access requests reviewed and approved before granting? 3. Are logs of provider access requests retained for compliance?_x000D_ | K9: 1. Customer Lockbox configuration status (Azure Portal → Security → Customer Lockbox). 2. Support request approval logs. 3. Audit log exports showing provider support access | L9: 3

Sheet Data protection
A1: Control ID | B1: Control Title | C1: Security Principle | D1: Azure Guidance | E1: MCSB Control ID Mapping | F1: CIS Mapping (v8) | G1: NIST SP 800-53 Mapping | H1: PCI-DSS Mapping (v3.2.1) | I1: CSA CCM Control ID | K1: Assessment Question | L1: Evidence to Collect | M1: Evidence Count | N1: Available Evidence Count | O1: Compliance Status | P1: Risk Severity (if non-compliant) | Q1: Implementation Gap | R1: Notes/Comments
A2: CSF-AZ-DP-01 | B2: Discover, classify, and label sensitive data | C2: Establish and maintain an inventory of the sensitive data, based on the defined sensitive data scope. Use tools to discover, classify and label the in- scope sensitive data. | D2: Use tools such as Microsoft Purview, which combines the former Azure Purview and Microsoft 365 compliance solutions, and Azure SQL Data Discovery and Classification to centrally scan, classify, and label the sensitive data that reside in the Azure, on-premises, Microsoft 365, and other locations. | E2: DP-1 | F2: 3.2, 3.7, 3.13 | G2: RA-2, SC-28 | H2: A3.2 | I2: DSP-01, DSP-02, DSP-03 | K2: 1. How is sensitive data discovered across structured (SQL, Cosmos DB) and unstructured (Storage, SharePoint, Exchange) repositories? 2. What tools (Microsoft Purview, AIP) are in use for automated scanning and classification? 3. Are classification labels enforced and synchronized across hybrid/M365 workloads? 4. How is coverage validated for new data sources (e.g., onboarding of new Azure SQL servers)? | L2: 1. Microsoft Purview scan/job logs with discovered data assets. 2. Export of SQL sys. sensitivity_classifications. 3. Sensitivity labels configuration in AIP/Purview. 4. Sample classified records/screenshots of label enforcement in Office/SharePoint. | M2: 4
A3: CSF-AZ-DP-02 | B3: Monitor anomalies and threats targeting sensitive data | C3: Monitor for anomalies around sensitive data, such as unauthorized transfer of data to locations outside of enterprise visibility and control. This typically involves monitoring for anomalous activities (large or unusual transfers) that could indicate unauthorized data exfiltration. | D3: Use Azure Information protection (AIP) to monitor the data that has been classified and labeled. Use Microsoft Defender for Storage, Microsoft Defender for SQL, Microsoft Defender for open-source relational databases, and Microsoft Defender for Cosmos DB to alert on anomalous transfer of information that might indicate unauthorized transfers of sensitive data information. Note: If required for compliance of data loss prevention (DLP), you can use a host-based DLP solution from Azure Marketplace or a Microsoft 365 DLP solution to enforce detective and/or preventative controls to prevent data exfiltration. | E3: DP-2 | F3: 3.13 | G3: AC-4, SI-4 | H3: A3.2 | I3: DSP-04, DSP-05, EKM-01 | K3: 1. Which monitoring services (Defender for Storage, Defender for SQL, Sentinel analytics) are enabled? 2. How is anomalous exfiltration (large/unusual transfers, cross-region copy) detected? 3. Are DLP policies deployed for both cloud (M365 DLP, Azure DLP connectors) and endpoint paths? 4. How are false positives tuned in alert rules? | L3: 1. Alerts from Microsoft Defender for SQL, Storage, CosmosDB. 2. Sentinel queries/rules for anomalous transfer activity. 3. DLP incident reports from Microsoft Purview Information Protection. 4. Log Analytics export of activity anomalies (copy, delete, large volume). | M3: 4
A4: CSF-AZ-DP-03 | B4: Encrypt sensitive data in transit | C4: Protect the data in transit against 'out of band' attacks (such as traffic capture) using encryption to ensure that attackers cannot easily read or modify the data. Set the network boundary and service scope where data in transit encryption is mandatory inside and outside of the network. While this is optional for traffic on private networks, this is critical for traffic on external and public networks. | D4: Enforce secure transfer in services such as Azure Storage, where a native data in transit encryption feature is built in. Enforce HTTPS for web application workloads and services by ensuring that any clients connecting to your Azure resources use transport layer security (TLS) v1.2 or later. For remote management of VMs, use SSH (for Linux) or RDP/TLS (for Windows) instead of an unencrypted protocol. For remote management of Azure virtual machines, use SSH (for Linux) or RDP/TLS (for Windows) instead of an unencrypted protocol. For secure file transfer, use the SFTP/FTPS service in Azure Storage Blob, App Service apps, and Function apps, instead of using the regular FTP service. Note: Data in transit encryption is enabled for all Azure traffic traveling between Azure datacenters. TLS v1.2 or later is enabled on most Azure services by default. And some services such as Azure Storage and Application Gateway can enforce TLS v1.2 or later on the server side. | E4: DP-3 | F4: 3.1 | G4: SC-8 | H4: 3.5, 3.6, 4.1 | I4: EKM-02, IPY-03, IVS-07 | K4: 1. Are TLS 1.2+ enforced for all public endpoints (App Gateway, Storage, Key Vault)? 2. Is "Secure transfer required" enabled on all Storage accounts? 3. Are SSH/RDP over TLS configured for VM management? 4. Are legacy or weak cipher suites blocked? | L4: 1. App Gateway / Front Door TLS configuration output. 2. VM access logs confirming RDP over TLS / SSH key-based authentication. 3. Wireshark/tcpdump validation of TLS handshakes. 4. Azure Policy compliance for "Secure transfer required." | M4: 4
A5: CSF-AZ-DP-04 | B5: Enable data at rest encryption by default | C5: To complement access controls, data at rest should be protected against 'out of band' attacks (such as accessing underlying storage) using encryption. This helps ensure that attackers cannot easily read or modify the data. | D5: Many Azure services have data at rest encryption enabled by default at the infrastructure layer using a service-managed key. These service-managed keys are generated on the customer’s behalf and automatically rotated every two years. Where technically feasible and not enabled by default, you can enable data at rest encryption in the Azure services, or in your VMs at the storage level, file level, or database level. | E5: DP-4 | F5: 3.11 | G5: SC-28 | H5: 3.4, 3.5 | I5: EKM-03, IPY-03, IVS-07 | K5: 1. Is encryption enabled by default on Storage, SQL DB, Cosmos DB, and managed disks? 2. Are custom images/disks checked for BitLocker/DM-crypt? 3. How is double encryption applied in critical workloads? 4. How often are service-managed keys rotated? | L5: 1. Azure Storage account properties JSON ( encryption. services. * ). 2. SQL Transparent Data Encryption status ( sys.dm_database_encryption_keys ). 3. Disk encryption settings via az vm encryption show. 4. Azure Policy compliance report for "encryption at rest." | M5: 4
A6: CSF-AZ-DP-05 | B6: Use customer-managed key option in data at rest encryption when required | C6: If required for regulatory compliance, define the use case and service scope where customer-managed key option is needed. Enable and implement data at rest encryption using customer-managed keys in services. | D6: Azure also provides an encryption option using keys managed by yourself (customer-managed keys) for most services. Azure Key Vault Standard, Premium, and Managed HSM are natively integrated with many Azure Services for customer-managed key use cases. You may use Azure Key Vault to generate your key or bring your own keys. However, using the customer-managed key option requires additional operational effort to manage the key lifecycle. This may include encryption key generation, rotation, revoke, and access control, etc. | E6: DP-5 | F6: 3.11 | G6: SC-12, SC-28 | H6: 3.4, 3.5, 3.6 | I6: EKM-04, EKM-06, EKM-07 | K6: 1. Which services are using CMKs instead of Microsoft-managed keys? 2. How are keys created, rotated, and retired in Key Vault/HSM? 3. Is BYOK/HYOK used for regulatory workloads (finance, healthcare)? 4. Are CMK policies (rotation, expiration) enforced by automation? | L6: 1. Azure Key Vault key properties with rotation policy JSON. 2. Audit logs for CMK usage (wrap/unwrap, encrypt/decrypt). 3. Service configs (Storage/SQL) referencing CMK URIs. 4. Proof of HSM-protected key use (Managed HSM configuration). | M6: 4
A7: CSF-AZ-DP-06 | B7: Use a secure key management process | C7: Document and implement an enterprise cryptographic key management standard, processes, and procedures to control your key lifecycle. When there is a need to use customer-managed key in the services, use a secured key vault service for key generation, distribution, and storage. Rotate and revoke your keys based on the defined schedule and when there is a key retirement or compromise. | D7: Use Azure Key Vault to create and control your encryption keys life cycle, including key generation, distribution, and storage. Rotate and revoke your keys in Azure Key Vault and your service based on the defined schedule and when there is a key retirement or compromise. Require a certain cryptographic type and minimum key size when generating keys. When there is a need to use customer-managed key (CMK) in the workload services or applications, ensure you follow the best practices: Use a key hierarchy to generate a separate data encryption key (DEK) with your key encryption key (KEK) in your key vault. Ensure keys are registered with Azure Key Vault and implemented via key IDs in each service or application. To maximize the key material lifetime and portability, bring your own key (BYOK) to the services (i.e., importing HSM-protected keys from your on-premises HSMs into Azure Key Vault). Follow the recommended guideline to perform the key generation and key transfer. Note: Refer to the below for the FIPS 140-2 level for Azure Key Vault types and FIPS compliance/validation level. Software-protected keys in vaults (Premium & Standard SKUs): FIPS 140-2 Level 1 HSM-protected keys in vaults (Premium SKU): FIPS 140-2 Level 2 HSM-protected keys in Managed HSM: FIPS 140-2 Level 3 Azure Key Vault Premium uses a shared HSM infrastructure in the backend. Azure Key Vault Managed HSM uses dedicated, confidential service endpoints with a dedicated HSM for when you need a higher level of key security. | E7: DP-6 | F7: N/A | G7: IA-5, SC-12, SC-28 | H7: 3.6 | I7: EKM-08, EKM-09, EKM-10 | K7: 1. How are cryptographic keys generated (manual, API, HSM)? 2. Are expired/unused keys deleted? 3. Are access permissions for key operations reviewed regularly? | L7: 1. Azure Key Vault audit logs ( OperationName = Createkey and Deletekey ) from Log Analytics. 2. Managed HSM FIPS compliance export ( az keyvault show -- hsm-name <hsm> ). 3. Proof of key versioning: az keyvault key list-versions -- vault-name <vault> -- name <keyName>. 4. Azure AD PIM assignments or RBAC export showing who can perform wrapkey / unwrapKey. 5. Policy assignment screenshot enforcing "Key Vault keys should have an expiration date." | M7: 5
A8: CSF-AZ-DP-07 | B8: Use a secure certificate management process | C8: Document and implement an enterprise certificate management standard, processes and procedures which includes the certificate lifecycle control, and certificate policies (if a public key infrastructure is needed). Ensure certificates used by the critical services in your organization are inventoried, tracked, monitored, and renewed timely using automated mechanism to avoid service disruption. | D8: Use Azure Key Vault to create and control the certificate lifecycle, including the creation/import, rotation, revocation, storage, and purge of the certificate. Ensure the certificate generation follows the defined standard without using any insecure properties, such as insufficient key size, overly long validity period, insecure cryptography and so on. Setup automatic rotation of the certificate in Azure Key Vault and supported Azure services based on the defined schedule and when a certificate expires. If automatic rotation is not supported in the frontend application, use a manual rotation in Azure Key Vault. Avoid using a self-signed certificate and wildcard certificate in your critical services due to the limited security assurance. Instead, you can create public signed certificates in Azure Key Vault. The following Certificate Authorities (CAs) are the partnered providers that are currently integrated with Azure Key Vault. DigiCert: Azure Key Vault offers OV TLS/SSL certificates with DigiCert. GlobalSign: Azure Key Vault offers OV TLS/SSL certificates with GlobalSign. Note: Use only approved CA and ensure that known bad root/intermediate certificates issued by these CAs are disabled. | E8: DP-7 | F8: N/A | G8: IA-5, SC-12, SC-17 | H8: 3.6 | I8: EKM-11, EKM-12 | K8: 1. What process ensures only approved Certificate Authorities (CAs) are used? 2. How are cert renewals automated? 3. How is certificate expiry monitored and alerted? | L8: 1. Key Vault certificate inventory ( az keyvault certificate list ). 2. Azure Monitor alert rule JSON for Microsoft.KeyVault/certificates/nearExpiry. 3. Sentinel query results showing certificate expiration alerts triggered in last 90 days. 4. Documentation or config file showing integration with enterprise CA or DigiCert API. | M8: 4
A9: CSF-AZ-DP-08 | B9: Ensure security of key and certificate repository | C9: Ensure the security of the key vault service used for the cryptographic key and certificate lifecycle management. Harden your key vault service through access control, network security, logging and monitoring and backup to ensure keys and certificates are always protected using the maximum security. | D9: Secure your cryptographic keys and certificates by hardening your Azure Key Vault service through the following controls: Implement access control using RBAC policies in Azure Key Vault Managed HSM at the key level to ensure the least privilege and separation of duties principles are followed. For example, ensure separation of duties are in place for users who manage encryption keys so they do not have the ability to access encrypted data, and vice versa. For Azure Key Vault Standard and Premium, create unique vaults for different applications to ensure the least privilege and separation of duties principles are followed. Turn on Azure Key Vault logging to ensure critical management plane and data plane activities are logged. Secure the Azure Key Vault using Private Link and Azure Firewall to ensure minimal exposure of the service Use managed identity to access keys stored in Azure Key Vault in your workload applications. When purging data, ensure your keys are not deleted before the actual data, backups and archives are purged. Backup your keys and certificates using Azure Key Vault. Enable soft delete and purge protection to avoid accidental deletion of keys.When keys need to be deleted, consider disabling keys instead of deleting them to avoid accidental deletion of keys and cryptographic erasure of data. For bring your own key (BYOK) use cases, generate keys in an on-premises HSM and import them to maximize the lifetime and portability of the keys. Never store keys in plaintext format outside of the Azure Key Vault. Keys in all key vault services are not exportable by default. Use HSM-backed key types (RSA-HSM) in Azure Key Vault Premium and Azure Managed HSM for the hardware protection and the strongest FIPS levels. Enable Microsoft Defender for Key Vault for Azure-native, advanced threat protection for Azure Key Vault, providing an additional layer of security intelligence. | E9: DP-8 | F9: N/A | G9: IA-5, SC-12, SC-17 | H9: 3.6 | I9: EKM-13, IVS-02, LOG-02 | K9: 1. Who has administrative access to Key Vault and Managed HSM? 2. Are vaults protected by network ACLs and private endpoints? 3. Are purge protection and soft delete enabled? 4. Are all access events logged and forwarded to SIEM? 5. Are alerting rules in place for abnormal access attempts? | L9: 1. RBAC role assignment dump for Key Vault: az role assignment list -- scope <vaultResourceID>. 2. Vault network restriction config ( az keyvault show -- name <vault> -- query properties.networkAcls ). 3. Vault properties confirming soft delete/purge protection ( enablePurgeProtection: true ). 4. Sentinel workbook screenshot showing ingestion of Key Vault diagnostic logs. 5. Export of Azure Policy compliance: "Key Vault should have purge protection enabled." | M9: 5
A10: CSF-AZ-DP-09 | B10: Secrets management in use for applications | C10: Application secrets are stored in a secrets manager or vaulting solution. | D10: Azure Key Vault is in use | J10: APP-03.4 | K10: Is the organization currently following the Azure Guidance ? | L10: Confirmation of the Assessment question | M10: 1

Sheet Asset management
A1: Control ID | B1: Control Title | C1: Security Principle | D1: Azure Guidance | E1: MCSB Control ID Mapping | F1: CIS Mapping (v8) | G1: NIST SP 800-53 Mapping | H1: PCI-DSS Mapping (v3.2.1) | I1: CSA CCM Control ID | J1: Assessment Question | K1: Evidence to Collect | L1: Evidence Count | M1: Available Evidence Count | N1: Compliance Status | O1: Risk Severity (if non-compliant) | P1: Implementation Gap | Q1: Notes/Comments
A2: CSF-AZ-AM-01 | B2: Track asset inventory and their risks | C2: Track your asset inventory by query and discover all your cloud resources. Logically organize your assets by tagging and grouping your assets based on their service nature, location, or other characteristics. Ensure your security organization has access to a continuously updated inventory of assets. Ensure your security organization can monitor the risks to cloud assets by always having security insights and risks aggregated centrally. | D2: The Microsoft Defender for Cloud inventory feature and Azure Resource Graph can query for and discover all resources in your subscriptions, including Azure services, applications, and network resources. Logically organize assets according to your organization's taxonomy using tags as well as other metadata in Azure (Name, Description, and Category). Ensure that security organizations have access to a continuously updated inventory of assets on Azure. Security teams often need this inventory to evaluate their organization's potential exposure to emerging risks, and as an input for continuous security improvements. Ensure security organizations are granted Security Reader permissions in your Azure tenant and subscriptions so they can monitor for security risks using Microsoft Defender for Cloud. Security Reader permissions can be applied broadly to an entire tenant (Root Management Group) or scoped to management groups or specific subscriptions. | E2: AM-1 | F2: 1.1, 1.5, 2.1, 2.4 | G2: CM-8, PM-5 | H2: 2.4 | I2: GRM-01, IPY-02, TVM-01 | J2: 1. How are all Azure resources (VMs, storage, databases, networking) inventoried? 2. Is the inventory enriched with tags/metadata for classification? 3. How does the security team access this inventory? 4. Is risk information (e.g., Defender for Cloud security score) linked to asset records? | K2: 1. Azure Resource Graph query export: az graph query -q "Resources | summarize count() by type" 2. Microsoft Defender for Cloud > Inventory export (CSV of resources + security status). 3. Tenant-level RBAC check: az role assignment list -- role "Security Reader" showing security team access. 4. Tag compliance report from Azure Policy ("Resources should be tagged with environment/owner"). 5. Risk findings mapped to assets (screenshot of Defender for Cloud Security Posture per asset). | L2: 5
A3: CSF-AZ-AM-02 | B3: Use only approved services | C3: Ensure that only approved cloud services can be used, by auditing and restricting which services users can provision in the environment. | D3: Use Azure Policy to audit and restrict which services users can provision in your environment. Use Azure Resource Graph to query for and discover resources within their subscriptions. You can also use Azure Monitor to create rules to trigger alerts when a non-approved service is detected. | E3: AM-2 | F3: 2.5, 2.6 , 2.7, 4.8 | G3: CM-8, PM-5 | H3: 6.3 | I3: AAc-02, GRM-02, TVM-02 | J3: 1. How are unapproved Azure services restricted? 2. Which Azure Policies deny or audit new resource types? 3. How is non-compliance with approved services detected? | K3: 1. Azure Policy definition export: az policy assignment list -- query "[?policyDefinitionId == '/providers/Microsoft.Authorj 2. Resource Graph query results showing services in use: az graph query -q "Resources | summarize count() by type" 3. Azure Monitor alert rule JSON for detecting non-approved resource types. 4. Policy compliance report showing blocked/denied deployments (portal screenshot or CSV). | L3: 4
A4: CSF-AZ-AM-03 | B4: Ensure security of asset lifecycle management | C4: Ensure security attributes or configurations of the assets are always updated during the asset lifecycle. | D4: Establish or update security policies/process that address asset lifecycle management processes for potentially high impact modifications. These modifications include changes to identity providers and access, data sensitivity level, network configuration, and administrative privilege assignment. Identify and remove Azure resources when they are no longer needed. | E4: AM-3 | F4: 1.1, 2.1 | G4: CM-8, CM-7 | H4: 2.4 | I4: CCC-02, TVM-03 | J4: 1. How are decommissioned Azure resources (VMs, storage, databases) securely removed? 2. Are changes to identity providers, network configuration, or privileged assignments logged and reviewed? 3. Is there automation to detect and clean up unused resources? | K4: 1. Activity Log export showing Delete operations for resource groups/VMs: az monitor activity-log list -- resource-group <rg> -- status Succeeded -- query "[?operz 2. Azure Policy assignment enforcing "Resources must have an expiration date tag." 3. Microsoft Defender for Cloud recommendations report (unused or orphaned resources flagged). 4. Example cleanup automation script in Azure Automation or Logic App (JSON runbook or execution logs). 5. Privileged role audit from Azure AD PIM showing admin assignment lifecycle. | L4: 5
A5: CSF-AZ-AM-04 | B5: Limit access to asset management | C5: Limit users' access to asset management features, to avoid accidental or malicious modification of the assets in your cloud. | D5: Azure Resource Manager is the deployment and management service for Azure. It provides a management layer that enables you to create, update, and delete resources (assets) in Azure. Use Azure AD Conditional Access to limit users' ability to interact with Azure Resource Manager by configuring "Block access" for the "Microsoft Azure Management" App. Use Azure Role-based Access Control (Azure RBAC) to assign roles to identities to control their permissions and access to Azure resources. For example, a user with only the 'Reader' Azure RBAC role can view all resources, but is not allowed to make any changes. Use Resource Locks to prevent either deletions or modifications to resources. Resource Locks may also be administered through Azure Blueprints. | E5: AM-4 | F5: 3.3 | G5: AC-3 | H5: N/A | I5: TVM-04, AAC-01, GRM-03 | J5: 1. Who is permitted to manage Azure resources (create, modify, delete)? 2. Are asset management permissions restricted to security/operations teams? 3. Is least privilege enforced for Resource Graph, Defender for Cloud inventory, and tagging operations? | K5: 1. RBAC export: az role assignment list -- scope /subscriptions/<subID> -- query "[?roleDefinitionName == 2. Check for assignments of security Reader and Resource Policy Contributor roles at tenant/root management group. 3. Activity Log entries showing asset creation/deletion - filter by privileged roles. 4. Azure AD PIM report showing eligible vs active assignments for asset management roles. | L5: 4
A6: CSF-AZ-AM-05 | B6: Use only approved applications in virtual machine | C6: Ensure that only authorized software executes by creating an allow list and block the unauthorized software from executing in your environment. | D6: Use Microsoft Defender for Cloud adaptive application controls to discover and generate an application allow list. You can also use ASC adaptive application controls to ensure that only authorized software can executes, and all unauthorized software is blocked from executing on Azure Virtual Machines. Use Azure Automation Change Tracking and Inventory to automate the collection of inventory information from your Windows and Linux VMs. Software name, version, publisher, and refresh time information are available from the Azure portal. To get the software installation date and other information, enable guest-level diagnostics and direct the Windows Event Logs to a Log Analytics workspace. Depending on the type of scripts, you can use operating system-specific configurations or third-party resources to limit users' ability to execute scripts in Azure compute resources. You can also use a third-party solution to discover and identify unapproved software. | E6: AM-5 | F6: 2.5, 2.6, 2.7, 4.8 | G6: CM-8, CM-7, CM-10, CM-11 | H6: 6.3 | I6: TVM-05, GRM-05 | J6: 1. Are application allowlists defined and enforced for Azure VMs? 2. How are unauthorized binaries or scripts detected/blocked? 3. Is inventory of installed applications collected and reviewed? 4. Is script execution (PowerShell, Bash) restricted by policy? | K6: 1. Microsoft Defender for Cloud Adaptive Application Controls policy export (JSON). 2. Azure Automation Change Tracking and Inventory export (list of installed software on Windows/Linux VMs). 3. Log Analytics query results showing blocked execution attempts ( SecurityEvent with "ApplicationBlocked"). 4. Policy compliance results: "Only approved software should run on machines." 5. OS-level config (e.g., PowerShell execution policy Get-ExecutionPolicy ) on sample VMs. | L6: 5

Sheet Logging and threat detection
A1: Control ID | B1: Control Title | C1: Security Principle | D1: Azure Guidance | E1: MCSB Control ID Mapping | F1: CIS Mapping (v8) | G1: NIST SP 800-53 Mapping | H1: PCI-DSS Mapping (v3.2.1) | I1: CSA CCM Control ID | K1: Assessment Question | L1: Evidence to Collect | M1: Evidence Count | N1: Available Evidence Count | O1: Compliance Status | P1: Risk Severity (if non-compliant) | Q1: Implementation Gap | R1: Notes/Comments
A2: CSF-AZ-LTD-01 | B2: Enable threat detection capabilities | C2: To support threat detection scenarios, monitor all known resource types for known and expected threats and anomalies. Configure your alert filtering and analytics rules to extract high-quality alerts from log data, agents, or other data sources to reduce false positives. | D2: Use the threat detection capability of Microsoft Defender for Cloud for the respective Azure services. For threat detection not included in Microsoft Defender services, refer to Microsoft Cloud Security Benchmark service baselines for the respective services to enable the threat detection or security alert capabilities within the service. Ingest alerts and log data from Microsoft Defender for Cloud, Microsoft 365 Defender, and log data from other resources into your Azure Monitor or Microsoft Sentinel instances to build analytics rules, which detect threats and create alerts that match specific criteria across your environment. For Operational Technology (OT) environments that include computers that control or monitor Industrial Control System (ICS) or Supervisory Control and Data Acquisition (SCADA) resources, use Microsoft Defender for IoT to inventory assets and detect threats and vulnerabilities. For services that do not have a native threat detection capability, consider collecting the data plane logs and analyze the threats through Microsoft Sentinel. | E2: LT-1 | F2: 8.11 | G2: AU-3, AU-6, AU-12, SI-4 | H2: 10.6, 10.8, A3.5 | I2: LOG-05, LOG-03, SEF-03 | K2: 1. Which Azure services have Defender threat detection enabled? 2. Are workloads integrated with Sentinel? | L2: 1. az security pricing list -- query "[?pricingTier == 'Standard']" - confirm which services have Defender enabled. 2. List of Defender alerts in last 90 days ( az security alert list -- query "[]. {Resource:resourceGroup, Alert:alertDisplayName}" ). 3. Sentinel connector inventory ( az sentinel data-connector list ). 4. Custom Sentinel rule JSON proving tuning. 5. Screenshot of Defender for Cloud recommendations per service. 6. Export of cost configuration for Defender (evidence that org pays for coverage). | M2: 6
A3: CSF-AZ-LTD-02 | B3: Enable threat detection for identity and access management | C3: Detect threats for identities and access management by monitoring the user and application sign-in and access anomalies. Behavioral patterns such as excessive number of failed login attempts, and deprecated accounts in the subscription, should be alerted. | D3: Azure AD provides the following logs that can be viewed in Azure AD reporting or integrated with Azure Monitor, Microsoft Sentinel or other SIEM/monitoring tools for more sophisticated monitoring and analytics use cases: Sign-ins: The sign-ins report provides information about the usage of managed applications and user sign-in activities. Audit logs: Provides traceability through logs for all changes done by various features within Azure AD. Examples of audit logs include changes made to any resources within Azure AD like adding or removing users, apps, groups, roles and policies. Risky sign-ins: A risky sign-in is an indicator for a sign-in attempt that might have been performed by someone who is not the legitimate owner of a user account. Users flagged for risk: A risky user is an indicator for a user account that might have been compromised. Azure AD also provides an Identity Protection module to detect and remediate risks related to user accounts and sign-in behaviors. Examples of risks include leaked credentials, sign-in from anonymous or malware linked IP addresses, password spray. The policies in Azure AD Identity Protection allow you to enforce risk-based MFA authentication in conjunction with Azure Conditional Access on user accounts. In addition, Microsoft Defender for Cloud can be configured to alert on deprecated accounts in the subscription and suspicious activities such as an excessive number of failed authentication attempts. In addition to the basic security hygiene monitoring, Microsoft Defender for Cloud's Threat Protection module can also collect more in-depth security alerts from individual Azure compute resources (such as virtual machines, containers, app service), data resources (such as SQL DB and storage), and Azure service layers. This capability allows you to see account anomalies inside the individual resources. | E3: LT-2 | F3: 8.11 | G3: AU-3, AU-6, AU-12, SI-4 | H3: 10.6, 10.8, A3.5 | I3: LOG-08, LOG-05, IAM-03 | K3: 1. Are Azure AD risky sign-ins and user risk policies enforced? 2. Are failed sign-in attempts generating alerts? 3. Is MFA enforced for risk-based access? | L3: 1. Azure AD Identity Protection risky sign-in report export. 2. Conditional Access policy JSON ( az ad conditional-access policy list ) showing "Require MFA" for risky sign-in. 3. Sentinel analytic rule for password spray detection (export rule JSON). | M3: 3
A4: CSF-AZ-LTD-03 | B4: Enable logging for security investigation | C4: Enable logging for your cloud resources to meet the requirements for security incident investigations and security response and compliance purposes. | D4: Enable logging capability for resources at the different tiers, such as logs for Azure resources, operating systems and applications inside in your VMs and other log types. Be mindful about different types of logs for security, audit, and other operational logs at the management/control plane and data plane tiers. There are three types of the logs available at the Azure platform: Azure resource log: Logging of operations that are performed within an Azure resource (the data plane). For example, getting a secret from a key vault or making a request to a database. The content of resource logs varies by the Azure service and resource type. Azure activity log: Logging of operations on each Azure resource at the subscription layer, from the outside (the management plane). You can use the Activity Log to determine what, who, and when for any write operations (PUT, POST, DELETE) taken on the resources in your subscription. There is a single Activity log for each Azure subscription. Azure Active Directory logs: Logs of the history of sign-in activity and audit trail of changes made in the Azure Active Directory for a particular tenant. You can also use Microsoft Defender for Cloud and Azure Policy to enable resource logs and log data collecting on Azure resources. | E4: LT-3 | F4: 8.2, 8.5, 8.12 | G4: AU-3, AU-6, AU-12, SI-4 | H4: 10.1, 10.2, 10.3 | I4: LOG-08, LOG-02, LOG-09 | K4: 1. Are logs from data services (SQL, Key Vault, Storage) centralized? 2. Is Azure Activity Log streamed to Log Analytics or Sentinel? 3. Is retention period aligned with compliance? 4. Are VM OS/application logs ingested? 5. Are log sources mapped against regulatory audit needs (PCI, SOX, HIPAA)? | L4: 1. Diagnostic settings export for multiple resource types (e.g., Key Vault, SQL DB). 2. Activity Log export configuration ( az monitor log-profiles list ). 3. Log Analytics retention setting ( az monitor log-analytics workspace show -- query retentionInDays ). 4. Log Analytics query proving VM logs ingestion ( Heartbeat table). 5. Sentinel workbook screenshot mapping log sources vs MITRE ATT&CK techniques. 6. Policy compliance export: "Resource logs should be enabled for ... " | M4: 6
A5: CSF-AZ-LTD-04 | B5: Enable network logging for security investigation | C5: Enable logging for your network services to support network-related incident investigations, threat hunting, and security alert generation. The network logs may include logs from network services such as IP filtering, network and application firewall, DNS, flow monitoring and so on. | D5: Enable and collect network security group (NSG) resource logs, NSG flow logs, Azure Firewall logs, and Web Application Firewall (WAF) logs, and logs from virtual machines via the network traffic data collection agent for security analysis to support incident investigations, and security alert generation. You can send the flow logs to an Azure Monitor Log Analytics workspace and then use Traffic Analytics to provide insights. Collect DNS query logs to assist in correlating other network data. | E5: LT-4 | F5: 8.2, 8.5, 8.6, 8.7, 13.6 | G5: AU-3, AU-6, AU-12, SI-4 | H5: 10.8 | I5: LOG-08, LOG-03, LOG-05 | K5: 1. Are NSG flow logs enabled on all VNets? 2. Is Traffic Analytics running for network flows? 3. Are DNS logs ingested? | L5: 1. NSG flow log status: az network watcher flow-log show -- nsg <nsgName> -- resource-group <rg> 2. Traffic Analytics config export ( az network watcher flow-log show -- query flowAnalyticsConfiguration ). 3. Azure Firewall diagnostic log settings export. | M5: 3
A6: CSF-AZ-LTD-05 | B6: Centralize security log management and analysis | C6: Centralize logging storage and analysis to enable correlation across log data. For each log source, ensure that you have assigned a data owner, access guidance, storage location, what tools are used to process and access the data, and data retention requirements. Use Cloud native SIEM if you don't have an existing SIEM solution for CSPs. or aggregate logs/alerts into your existing SIEM. | D6: Ensure that you are integrating Azure activity logs into a centralized Log Analytics workspace. Use Azure Monitor to query and perform analytics and create alert rules using the logs aggregated from Azure services, endpoint devices, network resources, and other security systems. In addition, enable and onboard data to Microsoft Sentinel which provides security information event management (SIEM) and security orchestration automated response (SOAR) capabilities. | E6: LT-5 | F6: 8.9, 8.11, 13.1 | G6: AU-3, AU-6, AU-12, SI-4 | H6: N/A | I6: LOG-05, LOG-08, LOG-02 | K6: 1. Are logs from Azure resources centralized into Log Analytics or Sentinel? 2. Which connectors (Azure AD, Defender, M365, AWS/GCP) are active? 3. Is the SIEM ingesting all required categories (Audit, Security, Diagnostics)? 4. Are analysts using a single pane of glass for correlation and investigation? | L6: 1. Sentinel data connector list: az sentinel data-connector list -- resource-group <rg> -- workspace-name <ws> 2. Screenshot of Sentinel workbooks/dashboard showing multi-source log ingestion. 3. Azure Monitor diagnostic settings export for at least 3 resource types (e.g., Storage, SQL, Key Vault). 4. Log ingestion volume per table in Log Analytics ( Usage | summarize TotalGB = sum(Quantity) by DataType ). 5. Export of SIEM correlation rules (JSON) demonstrating cross-log analytics. 6. Proof of external cloud connectors (AWS CloudTrail, GCP Audit Logs) in Sentinel. | M6: 6
A7: CSF-AZ-LTD-06 | B7: Configure log storage retention | C7: Plan your log retention strategy according to your compliance, regulation, and business requirements. Configure the log retention policy at the individual logging services to ensure the logs are archived appropriately. | D7: Logs such as Azure Activity Logs are retained for 90 days and then deleted. You should create a diagnostic setting and route the logs to another location (such as Azure Monitor Log Analytics workspace, Event Hubs or Azure Storage) based on your needs. This strategy also applies to other resource logs and resources managed by yourself such as logs in the operating systems and applications inside VMs. You have the log retention option as below: Use Azure Monitor Log Analytics workspace for a log retention period of up to 1 year or per your response team requirements. Use Azure Storage, Data Explorer or Data Lake for long-term and archival storage for greater than 1 year and to meet your security compliance requirements. Use Azure Event Hubs to forward logs to an external resource outside of Azure. | E7: LT-6 | F7: 8.3, 8.10 | G7: AU-11 | H7: 10.5, 10.7 | I7: LOG-02, LOG-17, LOG-08 | K7: 1. Is log retention configured to meet compliance (90 days, 1 year, 7 years)? 2. Are immutable/archival storage accounts used for long-term log retention? 3. Are retention settings aligned with incident response and regulatory audit requirements? | L7: 1. Log Analytics workspace retention setting: az monitor log-analytics workspace show -- query retentionInDays 2. Screenshot of Sentinel "Data retention" blade per workspace. 3. Azure Policy compliance for "Log Analytics workspaces should have at least X days retention." 4. Storage Account container properties showing WORM/Immutable blob retention enabled for archived logs. 5. Export of diagnostic settings proving logs are being sent to long-term storage (e.g., Azure Storage, Event Hub). | M7: 5
A8: CSF-AZ-LTD-07 | B8: Use approved time synchronization sources | C8: Use approved time synchronization sources for your logging time stamp which include date, time and time zone information. | D8: Microsoft maintains time sources for most Azure PaaS and SaaS services. For your compute resources operating systems, use a Microsoft default NTP server for time synchronization unless you have a specific requirement. If you need to stand up your own network time protocol (NTP) server, ensure you secure the UDP service port 123. All logs generated by resources within Azure provide time stamps with the time zone specified by default. | E8: LT-7 | F8: 8.4 | G8: AU-8 | H8: 10.4 | I8: LOG-08, LOG-02 | K8: 1. Are all VMs synchronized to Azure's NTP or approved enterprise NTP servers? 2. Are non-approved/external NTP sources blocked? 3. Do logs show consistent timestamps across all resource types? | L8: 1. Windows VM config: powershell w32tm /query /status 2. Linux VM config: timedatectl show | grep NTP 3. Azure Policy compliance for "Time synchronization settings should use approved NTP sources." 4. Sample log entries from Sentinel ( Heartbeat | project TimeGenerated ) showing consistent UTC timestamps. | M8: 4
A9: CSF-AZ-LTD-08 | B9: Core log collection established, but not necessarily consistent | C9: At this level, the core cloud management plane logs are collected, but this may not be centralized or consistent. At a minimum, cloud API logs (e.g., CloudTrail, Azure Activity Log, GCP Cloud Audit Log) are collected for a majority of cloud deployments. | D9: Azure Monitor is configured with at least one EventHub that sends Activity Logs to a Storage Account or external storage/SIEM | J9: LOG-02.1 | K9: Is the organization currently following the Azure Guidance ? | L9: Confirmation of the Assessment question | M9: 1
A10: CSF-AZ-LTD-09 | B10: Management plane API activity logs are consistently collected and centralized | C10: Cloud management plane logs are consistently and centrally collected | D10: Each Azure subscription has an EventHub that sends to the same destination | J10: LOG-03.1 | K10: Is the organization currently following the Azure Guidance ? | L10: Confirmation of the Assessment question | M10: 1
A11: CSF-AZ-LTD-10 | B11: CSP threat/detection feeds are enabled and collected for at least production environments | C11: All cloud providers include add-on security feeds that often require separate subscriptions. While these can incrementally increase costs, they can typically perform monitoring and alerting for active cloud threats that are difficult to otherwise obtain and build. These feeds should be enabled for at least production deployments, with the results feeding a SIEM or other monitoring platform. | D11: Defender for Cloud Standard is enabled in all subscriptions labeled production. If subscriptions are not labeled, pass if >50% of subscriptions use Defender | J11: LOG-03.2 | K11: Is the organization currently following the Azure Guidance ? | L11: Confirmation of the Assessment question | M11: 1
A12: CSF-AZ-LTD-11 | B12: Robust cloud platform security telemetry centrally collected | C12: Organizations should have a list of required security telemetry from their cloud providers, which will include multiple sources beyond just the management plane logs. These sources should include a mixture of CSP security feeds, service logs/events and workload logs. This control objective can be automatically assessed by looking for a mixture of common security telemetry feeds, but this needs to be backed by manual assessment because, in many cases, security telemetry will be collected using third-party tooling (especially for workload logs). | D12: Check that more than three of the following security sources are enabled in >50% of monitored subscriptions: * Azure Defender for Cloud CSPM * AAD sign in logs * AAD activity log | J12: LOG-04.1 | K12: Is the organization currently following the Azure Guidance ? | L12: Confirmation of the Assessment question | M12: 1
A13: CSF-AZ-LTD-12 | B13: Cloud-native threat detectors are enabled | C13: Cloud-native threat detectors monitor management plane and other sources for signs of cloud attacks. These are different than traditional threat detectors because they look for cloud platform activity—not necessarily network or workload activity—to indicate potential attacks. For this control objective, threat detectors beyond those built into the cloud platform's built-in threat monitoring service should be enabled (e.g., custom detectors, not just GuardDuty or Defender). These detectors can be implemented natively in the cloud platform, but will typically be run from an external SIEM or cloud detection and response (CDR) platform. Thus, this detector is difficult to automatically assess, unless the assessment tool itself includes the capability. | D13: Sentinel is running with default detectors (behavioral analytics) running | J13: LOG-04.2 | K13: Is the organization currently following the Azure Guidance ? | L13: Confirmation of the Assessment question | M13: 1

Sheet Incident response
A1: Control ID | B1: Control Title | C1: Security Principle | D1: Azure Guidance | E1: MCSB Control ID Mapping | F1: CIS Mapping (v8) | G1: NIST SP 800-53 Mapping | H1: PCI-DSS Mapping (v3.2.1) | I1: CSA CCM Control ID | J1: Assessment Question | K1: Evidence to Collect | L1: Evidence Count | M1: Available Evidence Count | N1: Compliance Status | O1: Risk Severity (if non-compliant) | P1: Implementation Gap | Q1: Notes/Comments
A2: CSF-AZ-IR-01 | B2: Preparation - update incident response plan and handling process | C2: Ensure your organization follows industry best practice to develop processes and plans to respond to security incidents on the cloud platforms. Be mindful about the shared responsibility model and the variances across IaaS, PaaS, and SaaS services. This will have a direct impact on how you collaborate with your cloud provider in incident response and handling activities, such as incident notification and triage, evidence collection, investigation, eradication, and recovery. Regularly test the incident response plan and handling process to ensure they're up to date. | D2: Update your organization's incident response process to include the handling of incidents in the Azure platform. Based on the Azure services used and your application nature, customize the incident response plan and playbook to ensure they can be used to respond to the incident in the cloud environment. | E2: IR-1 | F2: 17.4, 17.7 | G2: IR-4, IR-8 | H2: 10.8 | I2: SEF-01, SEF-02, SEF-03 | J2: 1. Is there an Azure-specific IR plan covering Sentinel, Defender for Cloud, and AAD? 2. When was the last IR tabletop exercise conducted? 3. Are runbooks/playbooks reviewed and updated after plan revisions? | K2: 1. IR plan version log with last modified timestamp ( SharePoint/Confluence version history ). 2. Sentinel playbook export: az sentinel automation-rule list -- resource-group <rg> -- workspace-name <ws> 3. Change history for IR runbooks in Azure Automation ( az automation runbook list .. resource-group <rg> ). 4. Evidence of simulated attack drill in Sentinel ( SecurityIncident | where Title contains "simulation" ). | L2: 4
A3: CSF-AZ-IR-02 | B3: Preparation - setup incident notification | C3: Ensure the security alerts and incident notifications from the cloud service provider's platform and your environments can be received by correct contact in your incident response organization. | D3: Set up security incident contact information in Microsoft Defender for Cloud. This contact information is used by Microsoft to contact you if the Microsoft Security Response Center (MSRC) discovers that your data has been accessed by an unlawful or unauthorized party. You also have options to customize incident alerts and notification in different Azure services based on your incident response needs. | E3: IR-2 | F3: 17.1, 17.3, 17.6 | G3: IR-4, IR-8, IR-5, IR-6 | H3: 12.1 | I3: SEF-04, SEF-02 | J3: 1. Is a security contact configured in Defender for Cloud? 2. Are incident alerts integrated with ticketing (ServiceNow, Jira) or paging (Teams, PagerDuty)? 3. Are alternate comms (SMS/email) tested for out-of-band notifications? | K3: 1. az security contact list -- query "[]. {Email: email, Phone: phone}". 2. Sentinel alert - Logic App connector export proving ServiceNow integration. 3. Azure Monitor action group configuration ( az monitor action-group list ). | L3: 3
A4: CSF-AZ-IR-03 | B4: Detection and analysis - create incidents based on high-quality alerts | C4: Ensure you have a process to create high-quality alerts and measure the quality of alerts. This allows you to learn lessons from past incidents and prioritize alerts for analysts, so they don't waste time on false positives. High-quality alerts can be built based on experience from past incidents, validated community sources, and tools designed to generate and clean up alerts by fusing and correlating diverse signal sources. | D4: Microsoft Defender for Cloud provides high-quality alerts across many Azure assets. You can use the Microsoft Defender for Cloud data connector to stream the alerts to Microsoft Sentinel. Microsoft Sentinel lets you create advanced alert rules to generate incidents automatically for an investigation. Export your Microsoft Defender for Cloud alerts and recommendations using the export feature to help identify risks to Azure resources. Export alerts and recommendations either manually or in an ongoing, continuous fashion. | E4: IR-3 | F4: 17.9 | G4: IR-4, IR-5, IR-7 | H4: 10.8 | I4: LOG-05, LOG-08, SEF-03 | J4: 1. Are Microsoft Defender alerts automatically converted into Sentinel incidents? 2. Is there deduplication/correlation to prevent alert flooding? 3. How is fidelity measured (false positives, true positives)? 4. Are alerts prioritized against MITRE ATT&CK techniques? | K4: 1. Sentinel analytics rule export ( az sentinel alert-rule list ). 2. Incident export where ProviderName == "Microsoft. Security". 3. KQL correlation query: Kusto : SecurityIncident | summarize count() by AlertProductNames 4. MITRE ATT&CK mapping workbook screenshot from Sentinel. 5. Log Analytics query showing false positive suppression rates. | L4: 5
A5: CSF-AZ-IR-04 | B5: Detection and analysis - investigate an incident | C5: Ensure the security operation team can query and use diverse data sources as they investigate potential incidents, to build a full view of what happened. Diverse logs should be collected to track the activities of a potential attacker across the kill chain to avoid blind spots. You should also ensure insights and learnings are captured for other analysts and for future historical reference. Use the cloud native SIEM and incident management solution if your organization does not have an existing solution to aggregate security logs and alerts information. Correlate incident data based on the data sourced from different sources to facility the incident investigations. | D5: Ensure your security operations team can query and use diverse data sources that are collected from the in-scope services and systems. In addition, it sources can also include: Identity and access log data: Use Azure AD logs and workload (such as operating systems or application level) access logs for correlating identity and access events. Network data: Use network security groups' flow logs, Azure Network Watcher, and Azure Monitor to capture network flow logs and other analytics information. Incident related activity data of from snapshots of the impacted systems, which can be obtained through: The azure virtual machine's snapshots capability, to create a snapshot of the running system's disk. The operating system's native memory dump capability, to create a snapshot of the running system's memory. The snapshot feature of other supported Azure services or your software's own capability, to create snapshots of the running systems. Microsoft Sentinel provides extensive data analytics across virtually any log source and a case management portal to manage the full lifecycle of incidents. Intelligence information during an investigation can be associated with an incident for tracking and reporting purposes. | E5: IR-4 | F5: N/A | G5: IR-4 | H5: 12.1 | I5: SEF-04, GRM-07 | J5: 1. Are telemetry sources (AAD sign-in, NSG flows, VM OS logs) ingested into Sentinel? 2. Are snapshots and forensic images taken during investigation? 3. Do analysts use standardized KQL queries/playbooks? | K5: 1. Sample KQL queries run during last incident investigation. 2. NSG flow log JSON export ( az network watcher flow-log show ). 3. VM snapshot list ( az snapshot list -- resource-group <rg> ). 4. Immutable storage container listing forensic memory dumps. | L5: 4
A6: CSF-AZ-IR-05 | B6: Detection and analysis - prioritize incidents | C6: Provide context to security operations teams to help them determine which incidents ought to first be focused on, based on alert severity and asset sensitivity defined in your organization’s incident response plan. Additionally, mark resources using tags and create a naming system to identify and categorize your cloud resources, especially those processing sensitive data. It is your responsibility to prioritize the remediation of alerts based on the criticality of the resources and environment where the incident occurred. | D6: Microsoft Defender for Cloud assigns a severity to each alert to help you prioritize which alerts should be investigated first. The severity is based on how confident Microsoft Defender for Cloud is in the finding or the analytics used to issue the alert, as well as the confidence level that there was malicious intent behind the activity that led to the alert. Similarly, Microsoft Sentinel creates alerts and incidents with an assigned severity and other details based on analytics rules. Use analytic rule templates and customize the rules according to your organization's needs to support incident prioritization. Use automation rules in Microsoft Sentinel to manage and orchestrate threat response in order to maximize your security operation's team efficiency and effectiveness, including tagging incidents to classify them. | E6: IR-5 | F6: 17.4, 17.9 | G6: IR-4 | H6: 12.1 | I6: CCC-05, SEF-05 | J6: 1. How are severity levels defined (system default vs custom rules)? 2. Are incidents tied to asset tags or business impact classifications? 3. Are SLA response times enforced across severities? 4. How are repeated incidents prioritized differently from new ones? | K6: 1. Sentinel incident export with severity metadata. 2. Azure Resource Graph query: Kusto : Resources | where tags. CriticalAsset == "true" 3. SLA compliance metrics from SOC ticketing integration. 4. Sentinel incident timeline export showing "repeat offenders." | L6: 4
A7: CSF-AZ-IR-06 | B7: Containment, eradication and recovery - automate the incident handling | C7: Automate the manual, repetitive tasks to speed up response time and reduce the burden on analysts. Manual tasks take longer to execute, slowing each incident and reducing how many incidents an analyst can handle. Manual tasks also increase analyst fatigue, which increases the risk of human error that causes delays and degrades the ability of analysts to focus effectively on complex tasks. | D7: Use workflow automation features in Microsoft Defender for Cloud and Microsoft Sentinel to automatically trigger actions or run a playbooks to respond to incoming security alerts. Playbooks take actions, such as sending notifications, disabling accounts, and isolating problematic networks. | E7: IR-6 | F7: N/A | G7: IR-4, IR-5, IR-6 | H7: 12.1 | I7: SEF-06, GRM-08 | J7: 1. Which incidents trigger automated SOAR playbooks? 2. What containment steps are executed automatically (block IP, isolate VM, disable account)? 3. How are manual approvals integrated into automated flows? | K7: 1. Sentinel automation rule JSON export. 2. Logic App runbook execution log for VM isolation. 3. Azure AD audit logs: Kusto: AuditLogs | where ActivityDisplayName == "Block user" 4. Approval logs/screenshots from playbooks requiring analyst confirmation. | L7: 4
A8: CSF-AZ-IR-07 | B8: Post-incident activity - conduct lessons learned and retain evidence | C8: Conduct lessons learned in your organization periodically and/or after major incidents, to improve your future capability in incident response and handling. Based on the nature of the incident, retain the evidence related to the incident for the period defined in the incident handling standard for further analysis or legal actions. | D8: Use the outcome from the lessons learned activity to update your incident response plan, playbook (such as a Microsoft Sentinel playbook) and reincorporate findings into your environments (such as logging and threat detection to address any gaps in logging) to improve your future capability in detecting, responding, and handling of incidents in Azure. Keep the evidence collected during the "Detection and analysis - investigate an incident step" such as system logs, network traffic dumps and running system snapshots in storage such as an Azure Storage account for immutable retention. | E8: IR-7 | F8: 17.8 | G8: IR-4 | H8: 12.1 | I8: SEF-07, SEF-03 | J8: 1. Are formal lessons-learned meetings conducted post-incident? 2. Is the IR plan/playbooks updated as a result of those findings? 3. Are forensic artifacts archived immutably? 4. How are learnings fed back into detection logic (rules, hunting queries)? 5. Is training updated for analysts after incidents? | K8: 1. Post-mortem report (export PDF from ticketing/Confluence). 2. Sentinel playbook change log ( az resource show .. ). 3. Storage immutability policy ( az storage container immutability-policy show ). 4. Updated Sentinel analytics rule JSON dated after the incident. 5. SOC training records showing refreshed scenarios. | L8: 5

Sheet Posture and vulnerability manag
A1: Control ID | B1: Control Title | C1: Security Principle | D1: Azure Guidance | E1: MCSB Control ID Mapping | F1: CIS Mapping (v8) | G1: NIST SP 800-53 Mapping | H1: PCI-DSS Mapping (v3.2.1) | I1: CSA CCM Control ID | K1: Assessment Question | L1: Evidence to Collect | M1: Evidence Count | N1: Available Evidence Count | O1: Compliance Status | P1: Risk Severity (if non-compliant) | Q1: Implementation Gap | R1: Notes/Comments
A2: CSF-AZ-PVM-01 | B2: Define and establish secure configurations | C2: Define the security configuration baselines for different resource types in the cloud. Alternatively, use configuration management tools to establish the configuration baseline automatically before or during resource deployment so the environment can be compliant by default after the deployment. | D2: Use the Microsoft Cloud Security Benchmark and service baseline to define your configuration baseline for each respective Azure offering or service. Refer to the Azure reference architecture and Cloud Adoption Framework landing zone architecture to understand the critical security controls and configurations that may be needed across Azure resources. Use Azure landing zone (and Blueprints) to accelerate the workload deployment by setting up configuration of services and application environments, including Azure Resource Manager templates, Azure RBAC controls, and Azure Policy. | E2: PV-1 | F2: 4.1, 4.2 | G2: CM-2, CM-6 | H2: 1.1 | I2: CCC-02 | K2: 1. Are secure configuration baselines defined for all Azure resources (laaS/PaaS/SaaS)? 2. Are baselines aligned with Microsoft Cloud Security Benchmark (MCSB) and service-specific baselines? 3. Are Azure Landing Zones, Blueprints, or ARM templates used to enforce these baselines? | L2: 1. Export of Azure Policy definitions/assignments ( az policy definition list, az policy assignment list ). 2. Azure Blueprints deployment logs or JSON definitions. 3. ARM/Bicep template files in source control. | M2: 3
A3: CSF-AZ-PVM-02 | B3: Audit and enforce secure configurations | C3: Continuously monitor and alert when there is a deviation from the defined configuration baseline. Enforce the desired configuration according to the baseline configuration by denying the non-compliant configuration or deploying a configuration. | D3: Use Microsoft Defender for Cloud to configure Azure Policy to audit and enforce configurations of your Azure resources. Use Azure Monitor to create alerts when there is a configuration deviation detected on the resources. Use Azure Policy [deny] and [deploy if not exist] rules to enforce secure configuration across Azure resources. For resource configuration audit and enforcement not supported by Azure Policy, you may need to write custom scripts or use third-party tooling to implement the configuration audit and enforcement. | E3: PV-2 | F3: 4.1, 4.2 | G3: CM-2, CM-6 | H3: 2.2 | I3: CCC-03 | K3: Are Azure Policy compliance scans running on all subscriptions and management groups? 2. Are [deny] and [deploylfNotExists] effects enforced for critical policies (e.g., disallow public IPs)? 3. Are compliance drifts generating alerts in Microsoft Defender for Cloud or Azure Monitor? 4. Are unsupported resource types handled with custom scripts or third-party tools? | L3: 1. Azure Policy compliance results ( az policy state list or Defender for Cloud Compliance blade). 2. Azure Activity Logs showing automatic remediation events. 3. Azure Monitor alert rules ( az monitor metrics alert list ). 4. Defender for Cloud recommendations export ( az security assessment list ). | M3: 4
A4: CSF-AZ-PVM-03 | B4: Define and establish secure configurations for compute resources | C4: Define the secure configuration baselines for your compute resources, such as VMs and containers. Use configuration management tools to establish the configuration baseline automatically before or during the compute resource deployment so the environment can be compliant by default after the deployment. Alternatively, use a pre-configured image to build the desired configuration baseline into the compute resource image template. | D4: Use Azure recommended operating system security baselines (for both Windows and Linux) as a benchmark to define your compute resource configuration baseline. Additionally, you can use a custom VM image (using Azure Image Builder) or container image with Azure Automanage Machine Configuration (formerly called Azure Policy Guest Configuration) and Azure Automation State Configuration to establish the desired security configuration. | E4: PV-3 | F4: 4.1 | G4: CM-2, CM-6 | H4: 2.2 | I4: IVS-08 | K4: 1. Are OS security baselines (Windows/Linux) applied to VMs using Microsoft Security Baselines? 2. Are custom hardened images built with Azure Image Builder or Packer? 3. Are container images configured with CIS/Microsoft benchmarks before deployment? 4. Are baseline images stored in a controlled Azure Compute Gallery? | L4: 1. Microsoft Security Baseline compliance reports from Defender for Cloud (VM assessment logs). 2. Image Builder JSON templates ( az image builder build list ). 3. Container registry scan results from Defender for Cloud ( az security assessment-metadata list -- query "containerVulnerability" ). 4. Azure Compute Gallery image version list ( az sig image-version list ). | M4: 4
A5: CSF-AZ-PVM-04 | B5: Audit and enforce secure configurations for compute resources | C5: Continuously monitor and alert when there is a deviation from the defined configuration baseline in your compute resources. Enforce the desired configuration according to the baseline configuration by denying the non-compliant configuration or deploying a configuration in compute resources. | D5: Use Microsoft Defender for Cloud and Azure Automanage Machine Configuration (formerly called Azure Policy Guest Configuration) to regularly assess and remediate configuration deviations on your Azure compute resources, including VMs, containers, and others. In addition, you can use Azure Resource Manager templates, custom operating system images, or Azure Automation State Configuration to maintain the security configuration of the operating system. Microsoft VM templates in conjunction with Azure Automation State Configuration can assist in meeting and maintaining security requirements. Use Change Tracking and Inventory in Azure Automation to track changes in virtual machines hosted in Azure, on-premises, and other cloud environments to help you pinpoint operational and environmental issues with software managed by the Distribution Package Manager. Install the Guest Attestation agent on virtual machines to monitor for boot integrity on confidential virtual machines. | E5: PV-4 | F5: 4.1 | G5: CM-2, CM-6 | H5: 2.2 | I5: TVM-07 | K5: 1. Are VM configurations continuously monitored with Azure Policy Guest Configuration / Automanage? 2. Are deviations from OS baselines flagged and auto-remediated? 3. Are unauthorized VM changes tracked with Azure Automation Change Tracking? 4. Are container images rescanned periodically for vulnerabilities? | L5: 1. Azure Policy Guest Configuration compliance logs ( az policy state list -- filter "resourceType eq 'Microsoft.GuestConfiguration'" ). 2. Automanage compliance reports ( az automanage configuration-profile-assignment list ). 3. Azure Automation Change Tracking & Inventory logs (Log Analytics query results). 4. Azure Container Registry vulnerability scan logs ( az acr repository show-manifests -- detail ). | M5: 4
A6: CSF-AZ-PVM-05 | B6: Perform vulnerability assessments | C6: Perform vulnerabilities assessment for your cloud resources at all tiers in a fixed schedule or on-demand. Track and compare the scan results to verify the vulnerabilities are remediated. The assessment should include all types of vulnerabilities, such as vulnerabilities in Azure services, network, web, operating systems, misconfigurations, and so on. Be aware of the potential risks associated with the privileged access used by the vulnerability scanners. Follow the privileged access security best practice to secure any administrative accounts used for the scanning. | D6: Follow recommendations from Microsoft Defender for Cloud for performing vulnerability assessments on your Azure virtual machines, container images, and SQL servers. Microsoft Defender for Cloud has a built-in vulnerability scanner for virtual machines. Use a third-party solution for performing vulnerability assessments on network devices and applications (e.g., web applications) Export scan results at consistent intervals and compare the results with previous scans to verify that vulnerabilities have been remediated. When using vulnerability management recommendations suggested by Microsoft Defender for Cloud, you can pivot into the selected scan solution's portal to view historical scan data. When conducting remote scans, do not use a single, perpetual, administrative account. Consider implementing JIT (Just In Time) provisioning methodology for the scan account. Credentials for the scan account should be protected, monitored, and used only for vulnerability scanning. Note: Microsoft Defender services (including Defender for servers, containers, App Service, Database, and DNS) embed certain vulnerability assessment capabilities. The alerts generated from Azure Defender services should be monitored and reviewed together with the result from Microsoft Defender for Cloud vulnerability scanning tool. | E6: PV-5 | F6: 5.5, 7.1, 7.5, 7.6 | G6: RA-3, RA-5 | H6: 6.1, 6.2, 6.6 | I6: TVM-06 | K6: 1. Are Azure VMs configured to receive automatic security/OS updates (Windows Update, Linux Update Management)? 2. Are patch cycles defined and enforced across all compute resources? 3. Are critical security patches deployed within SLA timelines? 4. Are update statuses centrally monitored through Defender for Cloud or Azure Update Management? | L6: 1. Update Compliance logs via Azure Automation Update Management (Log Analytics workspace query). 2. Defender for Cloud "Machines should have the latest security updates installed" assessment results ( az security assessment list ). 3. Windows/Linux VM update status ( Get-WUHistory on Windows, yum history list / apt list -- upgradable on Linux). 4. Azure Update Management job run reports ( az automation software-update-configuration list ). | M6: 4
A7: CSF-AZ-PVM-06 | B7: Rapidly and automatically remediate vulnerabilities | C7: Rapidly and automatically deploy patches and updates to remediate vulnerabilities in your cloud resources. Use the appropriate risk-based approach to prioritize the remediation of vulnerabilities. For example, more severe vulnerabilities in a higher value asset should be addressed as a higher priority. | D7: Use Azure Automation Update Management or a third-party solution to ensure that the most recent security updates are installed on your Windows and Linux VMs. For Windows VMs, ensure Windows Update has been enabled and set to update automatically. For third-party software, use a third-party patch management solution or Microsoft System Center Updates Publisher for Configuration Manager. | E7: PV-6 | F7: 7.2, 7.3, 7.4, 7.7 | G7: RA-3, RA-5, SI-2: FLAW REMEDIATION | H7: 6.1, 6.2, 6.5, 11.2 | I7: TVM-07 | K7: 1. Are vulnerability assessments enabled on all supported Azure VMs, databases, and containers? 2. Are vulnerability scan results integrated into Defender for Cloud for central visibility? 3. Are container images scanned in Azure Container Registry before deployment? 4. Are scan results exported and reviewed periodically for remediation prioritization? | L7: 1. Azure Container Registry vulnerability scan results ( az acr repository show-manifests -- detail -- repository <repo> ). 2. Defender for Cloud recommendation export ( az security assessment list -- resource-group <rg>). 3. Defender for Cloud VM vulnerability assessment results ( az security assessment-metadata list -- query "vmVulnerability" ). 4. SQL/Database vulnerability assessment export ( az sql db vulnerability-assessment-scan show ). | M7: 4
A8: CSF-AZ-PVM-07 | B8: Conduct regular red team operations | C8: Simulate real-world attacks to provide a more complete view of your organization's vulnerability. Red team operations and penetration testing complement the traditional vulnerability scanning approach to discover risks. Follow industry best practices to design, prepare and conduct this kind of testing to ensure it will not cause damage or disruption to your environment. This should always include discussing testing scope and constraints with relevant stakeholders and resource owners. | D8: As required, conduct penetration testing or red team activities on your Azure resources and ensure remediation of all critical security findings. Follow the Microsoft Cloud Penetration Testing Rules of Engagement to ensure your penetration tests are not in violation of Microsoft policies. Use Microsoft's strategy and execution of Red Teaming and live site penetration testing against Microsoft-managed cloud infrastructure, services, and applications. | E8: PV-7 | F8: 18.1, 18.2, 18.3, 18.4, 18.5 | G8: CA-8, RA-5 | H8: 6.6, 11.2, 11.3 | I8: TVM-08 | K8: 1. Is there an automated remediation process (via Azure Automation, Logic Apps, or Defender for Cloud workflow automation) for critical vulnerabilities? 2. Are vulnerabilities risk-scored and prioritized for remediation based on CVSS/Defender recommendations? 3. Is remediation status tracked across subscriptions and reported to security teams? 4. Are exceptions or deferred patches documented with compensating controls? | L8: 1. Defender for Cloud "Vulnerabilities in your virtual machines should be remediated" report. 2. Azure Automation remediation runbook logs (job execution logs). 3. Change tracking logs from Defender for Cloud (showing patched vs. unpatched). 4. Log Analytics queries showing open vs. closed vulnerabilities over time. | M8: 4
A9: CSF-AZ-PVM-08 | B9: Most deployments are organized in a hierarchy | C9: Deployments are part of an organization/tenant but may not be organized into a structured hierarchy. | D9: Most Azure subscriptions are managed within a single tenant (not multiple tenants) | J9: ORM-02.1 | K9: Is the organization currently following the Azure Guidance ? | L9: Confirmation of the Assessment question | M9: 1
A10: CSF-AZ-PVM-09 | B10: CSPM implemented and actively used | C10: A cloud security posture management tool is used to monitor for misconfigurations in cloud deployments. This control can be automated by either detecting another CSPM is in use or when the CSPM itself is performing the control assessment. | D10: Pass if Defender for Cloud is in use at the tenant level with Security Standards enabled | J10: ORM-03.1 | K10: Is the organization currently following the Azure Guidance ? | L10: Confirmation of the Assessment question | M10: 1
A11: CSF-AZ-PVM-10 | B11: Cloud service provider preventive policies are in use | C11: CSP preventive policies (AWS Service Control Policies, Azure Policies with deny rules, GCP policies) are in use and applied at the root of the hierarchy and to individual org units (OUs)/management groups (MGs)/folders. Using policies at multiple levels of the hierarchy doesn't necessarily indicate all the right policies are in place, but they are a good key indicator that a strategy exists and is being implemented. | D11: At least one policy with deny statements is applied at the root management group. At least two other policies with deny statements are applied to two or more other MGs. | J11: ORM-03.2 | K11: Is the organization currently following the Azure Guidance ? | L11: Confirmation of the Assessment question | M11: 1
A12: CSF-AZ-PVM-11 | B12: Deployments used to manage blast radius | C12: Multiple deployments (accounts/subscriptions/topics) are used within a hierarchical structure (multiple OUs/MGs/folders) to reduce the impact of security issues within any single deployment. For example, AWS accounts are in OUs, Azure subscriptions are in MGs and GCP Projects are in folders. | D12: More than three non-root MGs exist and >90% of subscriptions are in non-root Management Groups | J12: ORM-04.1 | K12: Is the organization currently following the Azure Guidance ? | L12: Confirmation of the Assessment question | M12: 1
A13: CSF-AZ-PVM-12 | B13: Cloud Service Provider preventive policies are consistently used | C13: CSP preventive policies (AWS Service Control Policies, Azure Policies with deny rules, GCP policies) are in use and applied at the root of the hierarchy and to all individual OUs/MGs/folders. | D13: At least one policy with deny statements is applied at the root management group. At least one other policy with deny statements is applied to all other MGs | J13: ORM-04.2 | K13: Is the organization currently following the Azure Guidance ? | L13: Confirmation of the Assessment question | M13: 1

Sheet Endpoint security
A1: Control ID | B1: Control Title | C1: Security Principle | D1: Azure Guidance | E1: MCSB Control ID Mapping | F1: CIS Mapping (v8) | G1: NIST SP 800-53 Mapping | H1: PCI-DSS Mapping (v3.2.1) | I1: CSA CCM Control ID | J1: Assessment Question | K1: Evidence to Collect | L1: Evidence Count | M1: Available Evidence Count | N1: Compliance Status | O1: Risk Severity (if non-compliant) | P1: Implementation Gap | Q1: Notes/Comments
A2: CSF-AZ-EPS-01 | B2: Use Endpoint Detection and Response (EDR) | C2: Enable Endpoint Detection and Response (EDR) capabilities for VMs and integrate with SIEM and security operations processes. | D2: Microsoft Defender for servers (with Microsoft Defender for Endpoint integrated) provides EDR capability to prevent, detect, investigate, and respond to advanced threats. Use Microsoft Defender for Cloud to deploy Microsoft Defender for servers on your endpoints and integrate the alerts to your SIEM solution such as Microsoft Sentinel. | E2: ES-1 | F2: 3.7 | G2: SC-3, SI-2, SI-3, SI-16 | H2: 11.5 | I2: UEM-04 | J2: 1. Are all Azure VMs onboarded to Microsoft Defender for Servers (with Defender for Endpoint)? 2. Are EDR alerts integrated into Microsoft Sentinel or SIEM for investigation? 3. Is coverage monitored to ensure no VM or server is excluded from EDR deployment? | K2: 1. Defender for Cloud "EDR coverage" compliance report ( az security assessment list -- query "[?name == 'microsoft.security/edrMonitoring']" ). 2. List of onboarded machines in Microsoft Defender for Endpoint ( Get-MpComputerStatus or Defender API export). 3. Microsoft Sentinel connector configuration logs showing Defender for Endpoint integration. | L2: 3
A3: CSF-AZ-EPS-02 | B3: Use modern anti-malware software | C3: Use anti-malware solutions (also known as endpoint protection) capable of real-time protection and periodic scanning. | D3: Microsoft Defender for Cloud can automatically identify the use of a number of popular anti-malware solutions for your virtual machines and on-premises machines with Azure Arc configured and report the endpoint protection running status and make recommendations. Microsoft Defender Antivirus is the default anti-malware solution for Windows server 2016 and above. For Windows server 2012 R2, use Microsoft Antimalware extension to enable SCEP (System Center Endpoint Protection). For Linux VMs, use Microsoft Defender for Endpoint on Linux for the endpoint protection feature. For both Windows and Linux, you can use Microsoft Defender for Cloud to discover and assess the health status of the anti-malware solution. | E3: ES-2 | F3: 10.1 | G3: SC-3, SI-2, SI-3, SI-16 | H3: 5.1 | I3: UEM-01 | J3: 1. Is Microsoft Defender Antivirus (Windows) or Defender for Endpoint (Linux) enabled on all VMs? 2. Are third-party anti-malware solutions detected and health-monitored in Defender for Cloud? 3. Are periodic scans and real-time protection enabled across all workloads? | K3: 1. Defender for Cloud "Endpoint Protection Not Installed/Not Healthy" recommendations ( az security assessment-metadata list -- query "[?contains(name, 'endpoint')]" ). 2. VM extension status for Microsoft Antimalware ( az vm extension list -- name IaaS Antimalware ). 3. Anti-malware health logs from Log Analytics workspace ( Heartbeat | where Solution contains "Antimalware" ). | L3: 3
A4: CSF-AZ-EPS-03 | B4: Ensure anti-malware software and signatures are updated | C4: Ensure anti-malware signatures are updated rapidly and consistently for the anti-malware solution. | D4: Follow recommendations in Microsoft Defender for Cloud to keep all endpoints up to date with the latest signatures. Microsoft Antimalware (for Windows) and Microsoft Defender for Endpoint (for Linux) will automatically install the latest signatures and engine updates by default. For third-party solutions, ensure the signatures are updated in the third-party anti-malware solution. | E4: ES-3 | F4: 10.2 | G4: SI-2, SI-3 | H4: 5.2 | I4: UEM-02 | J4: 1. Are malware signatures automatically updated on all Windows/Linux endpoints? 2. Are update failures (out-of-date signatures) flagged in Defender for Cloud? 3. Are signature update events logged and auditable for compliance? | K4: 1. Defender for Cloud assessment for "Endpoint protection should be up-to-date" ( az security assessment list -- query "[?name == 'microsoft.security/antimalwareUpToDate']" ). 2. Windows update logs ( Get-MpSignature for Defender AV). 3. Linux signature status logs ( mdatp health -- field definitions_updated ). 4. Log Analytics query on update events ( SecurityBaseline | where RecommendationName contains 'Antimalware signature' ). | L4: 4

Sheet Backup and recovery
A1: Control ID | B1: Control Title | C1: Security Principle | D1: Azure Guidance | E1: MCSB Control ID Mapping | F1: CIS Mapping (v8) | G1: NIST SP 800-53 Mapping | H1: PCI-DSS Mapping (v3.2.1) | I1: CSA CCM Control ID | J1: Assessment Question | K1: Evidence to Collect | L1: Evidence Count | M1: Available Evidence Count | N1: Compliance Status | O1: Risk Severity (if non-compliant) | P1: Implementation Gap | Q1: Notes/Comments
A2: CSF-AZ-B&R-01 | B2: Ensure regular automated backups | C2: Ensure backup of business-critical resources, either during resource creation or enforced through policy for existing resources. | D2: For Azure Backup supported resources (such as Azure VMs, SQL Server, HANA databases, Azure PostgreSQL Database, File Shares, Blobs or Disks), enable Azure Backup and configure the desired frequency and retention period. For Azure VM, you can use Azure Policy to have backup automatically enabled using Azure Policy. For resources or services not supported by Azure Backup, use the native backup capability provided by the resource or service. For example, Azure Key Vault provides a native backup capability. For resources/services that are neither supported by Azure Backup nor have a native backup capability, evaluate your backup and disaster needs, and create your own mechanism as per your business requirements. For example: If you use Azure Storage for data storage, enable blob versioning for your storage blobs which will allow you to preserve, retrieve, and restore every version of every object stored in your Azure Storage. Service configuration settings can usually be exported to Azure Resource Manager templates. | E2: BR-1 | F2: 11.2 | G2: CP-2, CP-4, CP-9 | H2: N/A | I2: BCR-09 | J2: 1. Are Azure Backup policies configured for all supported resources (VMs, SQL, HANA, PostgreSQL, File Shares, Blobs, Disks)? 2. Are Azure Policies applied to auto-enable backup at resource creation (e.g., VMs)? 3. Are unsupported services using their native backup features (e.g., Key Vault, Blob versioning)? | K2: 1. Azure Policy assignment export for "Deploy Backup on VMs" ( az policy assignment list ). 2. Azure Backup vault policy configuration ( az backup policy list -- vault-name <vault> ). 3. Azure Resource Graph query for resources missing backup association. 4. Backup job logs from Backup Center or Recovery Services Vault. | L2: 4
A3: CSF-AZ-B&R-02 | B3: Protect backup and recovery data | C3: Ensure backup data and operations are protected from data exfiltration, data compromise, ransomware/malware and malicious insiders. The security controls that should be applied include user and network access control, data encryption at-rest and in-transit. | D3: Use multi-factor-authentication and Azure RBAC to secure the critical Azure Backup operations (such as delete, change retention, updates to backup config). For Azure Backup supported resources, use Azure RBAC to segregate duties and enable fine grained access, and create private endpoints within your Azure Virtual Network to securely backup and restore data from your Recovery Services vaults. For Azure Backup supported resources, backup data is automatically encrypted using Azure platform-managed keys with 256-bit AES encryption. You can also choose to encrypt the backups using a customer managed key. In this case, ensure the customer-managed key in the Azure Key Vault is also in the backup scope. If you use a customer-managed key, use soft delete and purge protection in Azure Key Vault to protect keys from accidental or malicious deletion. For on-premises backups using Azure Backup, encryption-at-rest is provided using the passphrase you provide. Safeguard backup data from accidental or malicious deletion, such as ransomware attacks/attempts to encrypt or tamper backup data. For Azure Backup supported resources, enable soft delete to ensure recovery of items with no data loss for up to 14 days after an unauthorized deletion, and enable multifactor authentication using a PIN generated in the Azure portal. Also enable geo-redundant storage or cross-region restoration to ensure backup data is restorable when there is a disaster in primary region. You can also enable Zone-redundant Storage (ZRS) to ensure backups are restorable during zonal failures. | E3: BR-2 | F3: 11.3 | G3: CP-6, CP-9 | H3: 3.4 | I3: BCR-10 | J3: 1. Is backup data encrypted (platform-managed keys or CMK in Key Vault)? 2. Are soft delete and purge protection enabled for Recovery Services Vaults and Key Vault keys? 3. Is RBAC and MFA enforced for critical operations (delete, retention changes)? 4. Are backups geo-redundant or zone-redundant for resiliency? | K3: 1. Recovery Services Vault encryption settings ( az backup vault show -- name <vault> ). 2. Key Vault soft delete and purge protection status ( az keyvault show -- query "properties.enableSoftDelete" ). 3. Activity Logs for backup operations (delete/change) via Log Analytics. 4. Storage replication setting (GRS/ZRS) in Recovery Vault ( az backup vault backup- properties show ). | L3: 4
A4: CSF-AZ-B&R-03 | B4: Monitor backups | C4: Ensure all business-critical protectable resources are compliant with the defined backup policy and standard. | D4: Monitor your Azure environment to ensure that all your critical resources are compliant from a backup perspective. Use Azure Policy for backup to audit and enforce such controls. For Azure Backup supported resources, Backup Center helps you centrally govern your backup estate. Ensure critical backup operations (delete, change retention, updates to backup config) are monitored, audited, and have alerts in place. For Azure Backup supported resources, monitor overall backup health, get alerted to critical backup incidents, and audit triggered user actions on vaults. Note: Where applicable, also use built-in policies (Azure Policy) to ensure that your Azure resources are configured for backup. | E4: BR-3 | F4: 11.3 | G4: CP-9 | H4: N/A | I4: BCR-11 | J4: 1. Are backup jobs (success/failure) continuously monitored in Backup Center? 2. Are alerts configured for failed/critical backup incidents? 3. Are audit logs captured for sensitive backup operations (deletes, retention changes)? 4. Are compliance checks enforced via Azure Policy for backup-enabled resources? | K4: 1. Backup job status logs in Backup Center ( az backup job list -- vault-name <vault> ). 2. Azure Monitor alert rules for backup failures ( az monitor metrics alert list ). 3. Azure Activity Logs for backup vault operations. 4. Defender for Cloud compliance report for "resources should be backed up". | L4: 4
A5: CSF-AZ-B&R-04 | B5: Regularly test backup | C5: Periodically perform data recovery tests of your backup to verify that the backup configurations and availability of the backup data meets the recovery needs as per defined in the RTO (Recovery Time Objective) and RPO (Recovery Point Objective). | D5: Periodically perform data recovery tests of your backup to verify that the backup configurations and availability of the backup data meets the recovery needs as defined in the RTO and RPO. You may need to define your backup recovery test strategy, including the test scope, frequency and method as performing the full recovery test each time can be difficult. | E5: BR-4 | F5: 11.5 | G5: CP-4, CP-9 | H5: N/A | I5: BCR-12 | J5: 1. Are recovery tests performed periodically to validate RPO/RTO? 2. Are test restores executed for different resource types (VMs, Key Vault keys, SQL DBs)? 3. Is there a defined strategy for scope, frequency, and method of 4. Are test results documented and tracked for compliance? | K5: 1. Restore operation logs from Recovery Services Vault ( az backup recoveryconfig show ). 2. Log Analytics reports of restore operations (successful vs failed). 3. Evidence of restored test VMs, databases, or keys (resource creation events). 4. Test plans and runbooks stored in Automation or tracked in change management system. | L5: 4

Sheet DevOps security
A1: Control ID | B1: Control Title | C1: Security Principle | D1: Azure Guidance | E1: MCSB Control ID Mapping | F1: CIS Mapping (v8) | G1: NIST SP 800-53 Mapping | H1: PCI-DSS Mapping (v3.2.1) | I1: CSA CCM Control ID | J1: Assessment Question | K1: Evidence to Collect | L1: Evidence Count | M1: Available Evidence Count | N1: Compliance Status | O1: Risk Severity (if non-compliant) | P1: Implementation Gap | Q1: Notes/Comments
A2: CSF-AZ-DOS-01 | B2: Conduct threat modeling | C2: Perform threat modeling to identify the potential threats and enumerate the mitigating controls. Ensure your threat modeling serves the following purposes: Secure your applications and services in the production run-time stage. Secure the artifacts, underlying CI/CD pipeline and other tooling environment used for build, test, and deployment. The threat modeling at least should include the following aspects: Define the security requirements of the application. Ensure these requirements are adequately addressed in the threat modeling. Analyze application components, data connections and their relationship. Ensure this analysis also includes the upstream and downstream connections outside of your application scope. List the potential threats and attack vectors that your application components, data connections and upstream and downstream services may be exposed to. Identify the applicable security controls that can be used to mitigate the threats enumerated and identify any controls gaps (e.g., security vulnerabilities) that may require additional treatment plans. Enumerate and design the controls that can mitigate the vulnerabilities identified. | D2: Use threat modeling tools such as the Microsoft threat modeling tool with the Azure threat model template embedded to drive your threat modeling process. Use the STRIDE model to enumerate the threats from both internal and external and identify the controls applicable. Ensure the threat modeling process includes the threat scenarios in the DevOps process, such as malicious code injection through an insecure artifacts repository with misconfigured access control policy. If using a threat modeling tool is not applicable, you should, at minimum, use a questionnaire-based threat modeling process to identify the threats. Ensure the threat modeling or analysis results are recorded and updated when there is a major security-impact change in your application or in the threat landscape. | E2: DS-1 | F2: 16.10, 16.14 | G2: SA-15 | H2: 6.5, 12.2 | I2: AIS-02 | J2: 1. Has a threat model been developed for applications, CI/CD pipelines, and supporting infrastructure? 2. Are STRIDE or equivalent frameworks used to identify threats and mitigations? 3. Are threat models updated when major architectural or dependency changes occur? | K2: 1. Threat modeling tool outputs (Microsoft Threat Modeling Tool files or diagrams). 2. Change management records showing updated threat models after releases. 3. Stored threat model documents in repo/wiki (with last updated timestamps). | L2: 3
A3: CSF-AZ-DOS-02 | B3: Ensure software supply chain security | C3: Ensure your enterprise’s SDLC (Software Development Lifecycle) or process include a set of security controls to govern the in-house and third-party software components (including both proprietary and open-source software) where your applications have dependencies. Define gating criteria to prevent vulnerable or malicious components being integrated and deployed into the environment. The software supply chain security controls should at least include the following aspects: Properly manage a Software Bill of Materials (SBOM) by identifying the upstream dependencies required for the service/resource development, build, integration and deployment phase. Inventory and track the in-house and third-party software components for known vulnerability when there is a fix available in the upstream. Assess the vulnerabilities and malware in the software components using static and dynamic application testing for unknown vulnerabilities. Ensure the vulnerabilities and malware are mitigated using the appropriate approach. This may include source code local or upstream fix, feature exclusion and/or applying compensating controls if the direct mitigation is not available. If closed source third-party components are used in your production environment, you may have limited visibility to its security posture. You should consider additional controls such as access control, network isolation and endpoint security to minimize the impact if there is a malicious activity or vulnerability associated with the component. | D3: For the GitHub platform, ensure the software supply chain security through the following capability or tools from GitHub Advanced Security or GitHub’s native feature:- Use Dependency Graph to scan, inventory and identify all your project’s dependencies and related vulnerabilities through Advisory Database. Use Dependabot to ensure that the vulnerable dependency is tracked and remediated, and ensure your repository automatically keeps up with the latest releases of the packages and applications it depends on. Use GitHub's native code scanning capability to scan the source code when sourcing the code externally. Use Microsoft Defender for Cloud to integrate vulnerability assessment for your container image in the CI/CD workflow. For Azure DevOps, you can use third-party extensions to implement similar controls to inventory, analyze and remediate the third-party software components and their vulnerabilities. | E3: DS-2 | F3: 16.4, 16.6, 16.11 | G3: SA-12, SA-15 | H3: 6.3, 6.5 | I3: AIS-05 | J3: 1. Are dependencies scanned for vulnerabilities during builds (e.g., with GitHub Dependabot or Defender for Cloud)? 2. Are container images scanned before publishing to Azure Container Registry? 3. Are Software Bill of Materials (SBOM) maintained and updated for builds? 4. Are only trusted artifact registries used for dependencies? | K3: 1. GitHub Dependency Graph and Dependabot reports. 2. ACR vulnerability assessment results from Microsoft Defender for Containers ( az acr repository show-manifests -- detail ). 3. SBOM exports (CycloneDX, SPDX) stored in repo. 4. Azure Policy or Defender for Cloud compliance results on image scanning. | L3: 4
A4: CSF-AZ-DOS-03 | B4: Secure DevOps infrastructure | C4: Ensure the DevOps infrastructure and pipeline follow security best practices across environments including your build, test, and production stages. This typically includes the security controls for following scope: Artifact repositories that store source code, built packages and images, project artifacts and business data. Servers, services, and tooling that host CI/CD pipelines. CI/CD pipeline configuration. | D4: As part of applying the Microsoft Cloud Security Benchmark to your DevOps infrastructure security controls, prioritize the following controls: Protect artifacts and the underlying environment to ensure the CI/CD pipelines don’t become avenues to insert malicious code. For example, review your CI/CD pipeline to identify any misconfiguration in core areas of Azure DevOps such as Organization, Projects, Users, Pipelines (Build & Release), Connections, and Build Agent to identify any misconfigurations such as open access, weak authentication, insecure connection setup and so on. For GitHub, use similar controls to secure the Organization permission levels. Ensure your DevOps infrastructure is deployed consistently across development projects. Track compliance of your DevOps infrastructure at scale by using Microsoft Defender for Cloud (such as Compliance Dashboard, Azure Policy, Cloud Posture Management) or your own compliance monitoring tools. Configure identity/role permissions and entitlement policies in Azure AD, native services, and CI/CD tools in your pipeline to ensure changes to the pipelines are authorized. Avoid providing permanent “standing” privileged access to the human accounts such as developers or testers by using features such as Azure managed identifies and just-in-time access. Remove keys, credentials, and secrets from code and scripts used in CI/CD workflow jobs and keep them in a key store or Azure Key Vault. If you run self-hosted build/deployment agents, follow Microsoft Cloud Security Benchmark controls including network security, posture and vulnerability management, and endpoint security to secure your environment. | E4: DS-3 | F4: 16.7 | G4: CM-2, CM-6, AC-2, AC-3, AC-6 | H4: 2.2, 6.3, 7.1 | I4: IVS-09 | J4: 1. Are Azure DevOps/GitHub organizations configured with RBAC and MFA enforced? 2. Are secrets and credentials removed from code and stored in Azure Key Vault? 3. Are self-hosted build agents hardened and monitored? 4. Is CI/CD pipeline configuration audited for misconfigurations (open access, weak auth)? | K4: 1. Azure DevOps/GitHub audit logs ( az devops audit-log list , GitHub org audit log export). 2. Key Vault secret inventory ( az keyvault secret list ). 3. Defender for Cloud compliance dashboard for CI/CD resources. 4. Azure Monitor/Sentinel logs for pipeline changes. | L4: 4
A5: CSF-AZ-DOS-04 | B5: Integrate static application security testing into DevOps pipeline | C5: Ensure static application security testing (SAST) fuzzy testing, interactive testing, mobile application testing, are part of the gating controls in the CI/CD workflow. The gating can be set based on the testing results to prevent vulnerable packages from committing into the repository, building into the packages, or deploying into the production. | D5: Integrate SAST into your pipeline (e.g., in your infrastructure as code template) so the source code can be scanned automatically in your CI/CD workflow. Azure DevOps Pipeline or GitHub can integrate the below tools and third-party SAST tools into the workflow. GitHub CodeQL for source code analysis. Microsoft BinSkim Binary Analyzer for Windows and *nix binary analysis. Azure DevOps Credential Scanner (Microsoft Security DevOps extension) and GitHub native secret scanning for credential scan in the source code. | E5: DS-4 | F5: 16.12 | G5: SA-11 | H5: 6.3, 6.5 | I5: AIS-03 | J5: 1. Is SAST integrated in CI/CD pipelines (GitHub CodeQL, BinSkim, CredScan)? 2. Are builds blocked when critical SAST issues are detected? 3. Are SAST results stored and reviewed periodically? | K5: 1. GitHub Actions workflow YAML showing CodeQL integration. 2. Azure DevOps build pipeline logs with SAST job output. 3. Security DevOps extension/CodeQL scan reports in repos. | L5: 3
A6: CSF-AZ-DOS-05 | B6: Integrate dynamic application security testing into DevOps pipeline | C6: Ensure dynamic application security testing (DAST) are part of the gating controls in the CI/CD workflow. The gating can be set based on the testing results to prevent vulnerability from building into the packages or deploying into the production. | D6: Integrate DAST into your pipeline so the runtime application can be tested automatically in your CI/CD workflow set in Azure DevOps or GitHub. The automated penetration testing (with manual assisted validation) should also be part of the DAST. Azure DevOps Pipeline or GitHub supports the integration of third-party DAST tools into the CI/CD workflow. | E6: DS-5 | F6: 16.12 | G6: SA-11 | H6: 6.3, 6.5 | I6: AIS-03 | J6: 1. Are DAST scans executed as part of release pipelines (e.g., OWASP ZAP, Web Security Scanner)? 2. Are runtime application endpoints tested pre-production? 3. Are DAST results used as gating criteria for deployment approvals? | K6: 1. Azure DevOps release pipeline logs showing DAST scan job execution. 2. GitHub Actions workflows with DAST tool integrations. 3. Stored DAST reports in artifact storage or dashboards. | L6: 3
A7: CSF-AZ-DOS-06 | B7: Enforce security of workload throughout DevOps lifecycle | C7: Ensure the workload is secured throughout the entire lifecycle in development, testing, and deployment stage. Use Microsoft Cloud Security Benchmark to evaluate the controls (such as network security, identity management, privileged access and so on) that can be set as guardrails by default or shift left prior to the deployment stage. In particular, ensure the following controls are in place in your DevOps process:- Automate the deployment by using Azure or third-party tooling in the CI/CD workflow, infrastructure management (infrastructure as code), and testing to reduce human error and attack surface. Ensure VMs, container images and other artifacts are secure from malicious manipulation. Scan the workload artifacts (in other words, container images, dependencies, SAST and DAST scans) prior to the deployment in the CI/CD workflow Deploy vulnerability assessment and threat detection capability into the production environment and continuously use these capabilities in the run-time. | D7: Guidance for Azure VMs: Use Azure Shared Image Gallery to share and control access to your images by different users, service principals, or AD groups within your organization. Use Azure role-based access control (Azure RBAC) to ensure that only authorized users can access your custom images. Define the secure configuration baselines for the VMs to eliminate unnecessary credentials, permissions, and packages. Deploy and enforce configuration baselines through custom images, Azure Resource Manager templates, and/or Azure Policy guest configuration. Guidance for Azure container services: Use Azure Container Registry (ACR) to create your private container registry where granular access can be restricted through Azure RBAC, so only authorized services and accounts can access the containers in the private registry. Use Defender for Containers for vulnerability assessment of the images in your private Azure Container Registry. In addition, you can use Microsoft Defender for Cloud to integrate the container image scans as part of your CI/CD workflows. For Azure serverless services, adopt similar controls to ensure security controls "shift-left" to the stage prior to deployment. | E7: DS-6 | F7: 7.5, 7.6, 7.7, 16.1, 16.7 | G7: CM-2, CM-6, AC-2, AC-3, AC-6 | H7: 6.1, 6.2, 6.3 | I7: IVS-08 | J7: 1. Are VM/container images hardened with baseline configs (Shared Image Gallery, Azure Policy)? 2. Are container/VM images continuously scanned in runtime with Defender for Containers/Defender for Cloud? 3. Is laC (Terraform/ARM/Bicep) security scanning enabled pre-deployment? 4. Are runtime threat detection alerts monitored in Sentinel/Defender? | K7: 1. Shared Image Gallery/ACR access logs. 2. Defender for Cloud "Container image vulnerabilities" reports. 3. laC security scan logs (Checkov, Bicep linter, Azure DevOps Security DevOps extension). 4. Sentinel incident logs from Defender for Cloud signals. | L7: 4
A8: CSF-AZ-DOS-07 | B8: Enable logging and monitoring in DevOps | C8: Ensure your logging and monitoring scope includes non-production environments and CI/CD workflow elements used in DevOps (and any other development processes). The vulnerabilities and threats targeting these environments can introduce significant risks to your production environment if they are not monitored properly. The events from the CI/CD build, test and deployment workflow should also be monitored to identify any deviations in the CI/CD workflow jobs. | D8: Enable and configure the audit logging capabilities in non-production and CI/CD tooling environments (such as Azure DevOps and GitHub) used throughout the DevOps process. The events generated from Azure DevOps and the GitHub CI/CD workflow, including the build, test and deployment jobs, should also be monitored to identify any anomalous results. Ingest the above logs and events into Microsoft Sentinel or other SIEM tools through a logging stream or API to ensure the security incidents are properly monitored and triaged for handling. | E8: DS-7 | F8: 8.2, 8.5, 8.9, 8.11 | G8: AU-3, AU-6, AU-12, SI-4 | H8: 10.1, 10.2, 10.3, 10.6 | I8: LOG-04 | J8: 1. Are Azure DevOps and GitHub audit logs enabled and exported to Sentinel/Log Analytics? 2. Are CI/CD pipeline events (build, test, deploy) monitored for anomalies? 3. Are alerts generated for suspicious activities in DevOps environments? 4. Are logs from self-hosted build agents centralized in SIEM? | K8: 1. Azure DevOps audit streaming config ( az devops audit-log list -- org <org> ). 2. GitHub org audit log export. 3. Sentinel analytics rules monitoring DevOps logs. 4. Log Analytics queries for CI/CD job anomalies. | L8: 4

Sheet Governance and strategy
A1: Control ID | B1: Control Title | C1: Security Principle | D1: Azure Guidance | E1: MCSB Control ID Mapping | F1: CIS Mapping (v8) | G1: NIST SP 800-53 Mapping | H1: PCI-DSS Mapping (v3.2.1) | I1: CSA CCM Control ID | J1: Assessment Question | K1: Evidence to Collect | L1: Evidence Count | M1: Available Evidence Count | N1: Compliance Status | O1: Risk Severity (if non-compliant) | P1: Implementation Gap | Q1: Notes/Comments
A2: CSF-AZ-GS-01 | B2: Align organization roles, responsibilities and accountabilities | C2: Ensure that you define and communicate a clear strategy for roles and responsibilities in your security organization. Prioritize providing clear accountability for security decisions, educate everyone on the shared responsibility model, and educate technical teams on technology to secure the cloud. | D2: - | E2: GS-1 | F2: 14.9 | G2: PL-9, PM-10, PM-13, AT-1, AT-3 | H2: 2.4 | I2: GRC-01 | J2: 1. Have cloud security roles and responsibilities been formally documented and approved? 2. Are responsibilities aligned to Azure RBAC roles at tenant, subscription, and resource levels? 3. Is accountability reviewed periodically (e.g., during access reviews)? | K2: 1. Azure AD role assignments export ( az role assignment list ). 2. Security org chart with role-to-Azure-role mapping. 3. Access review reports from Azure AD Identity Governance. | L2: 3
A3: CSF-AZ-GS-02 | B3: Define and implement enterprise segmentation/separation of duties strategy | C3: Establish an enterprise-wide strategy to segment access to assets using a combination of identity, network, application, subscription, management group, and other controls. Carefully balance the need for security separation with the need to enable daily operation of the systems that need to communicate with each other and access data. Ensure that the segmentation strategy is implemented consistently in the workload, including network security, identity and access models, and application permission/access models, and human process controls. | E3: GS-2 | F3: 3.12 | G3: AC-4, SC-7, SC-2 | H3: 1.2, 6.4 | I3: IAM-10 | J3: 1. Is separation of duties enforced across management groups, subscriptions, and RBAC roles? 2. Are privileged functions (e.g., key management, identity admin) split across different 3. Is network/service segmentation aligned with enterprise security strategy? | K3: 1. RBAC role assignment exports ( az role assignment list -- all ). 2. Azure Policy enforcing subscription/management group segmentation. 3. Network topology/segmentation diagrams from Azure Resource Graph queries. | L3: 3
A4: CSF-AZ-GS-03 | B4: Define and implement data protection strategy | C4: Establish an enterprise-wide strategy for data protection in your cloud environment: Define and apply the data classification and protection standard in accordance with the enterprise data management standard and regulatory compliance to dictate the security controls required for each level of the data classification. Set up your cloud resource management hierarchy aligned to the enterprise segmentation strategy. The enterprise segmentation strategy should also be informed by the location of sensitive or business critical data and systems. Define and apply the applicable zero-trust principles in your cloud environment to avoid implementing trust based on network location within a perimeter. Instead, use device and user trust claims to gate access to data and resources. Track and minimize the sensitive data footprint (storage, transmission, and processing) across the enterprise to reduce the attack surface and data protection cost. Consider techniques such as one-way hashing, truncation, and tokenization in the workload where possible, to avoid storing and transmitting sensitive data in its original form. Ensure you have a full lifecycle control strategy to provide security assurance of the data and access keys. | E4: GS-3 | F4: 3.1, 3.7, 3.12 | G4: AC-4, SI-4, SC-8, SC-12, SC-17, SC-28, RA-2 | H4: 3.1, 3.2, 3.3, 3.4, 3.5, 3.6, 3.7, 4.1, A3.2 | I4: DSP-01 | J4: 1. Are all data services (storage, DBs, disks) encrypted at rest (PMK/CMK)? 2. Is encryption in transit (TLS 1.2+) enforced for data flows? 3. Are sensitive data types classified and labeled? | K4: 1. Azure Policy compliance export for encryption-at-rest ( az security assessment list ). 2. Storage/DB encryption config ( az storage account show -- query encryption, az sql db show -- query encryptionProtector ). 3. Microsoft Purview classification/labelling report export. | L4: 3
A5: CSF-AZ-GS-04 | B5: Define and implement network security strategy | C5: Establish a cloud network security strategy as part of your organization’s overall security strategy for access control. This strategy should include documented guidance, policy, and standards for the following elements: Design a centralized/decentralized network management and security responsibility model to deploy and maintain network resources. A virtual network segmentation model aligned with the enterprise segmentation strategy. An Internet edge and ingress and egress strategy. A hybrid cloud and on-premises interconnectivity strategy. A network monitoring and logging strategy. Up-to-date network security artifacts (such as network diagrams, reference network architecture). | E5: GS-4 | F5: 12.2, 12.4 | G5: AC-4, AC-17, CA-3, CM-1, CM-2, CM-6, CM-7, SC-1, SC-2, SC-5, SC-7, SC-20, SC-21, SI-4 | H5: 1.1, 1.2, 1.3, 1.5, 4.1, 6.6, 11.4, A2.1, A2.2, A2.3, A3.2 | I5: IVS-06 | J5: 1. Is segmentation and perimeter control enforced with NSGs, Firewalls, and Private Link? 2. Is DDoS Protection enabled for critical public endpoints? 3. Are flow logs from NSGs and Firewalls ingested into Log Analytics or Sentinel? | K5: 1. NSG/Firewall rules export ( az network nsg rule list, az network firewall network-rule list ). 2. DDoS Protection Plan config ( az network ddos-protection show ). 3. Network Watcher Flow Log status ( az network watcher flow-log show ). | L5: 3
A6: CSF-AZ-GS-05 | B6: Define and implement security posture management strategy | C6: Establish a policy, procedure and standard to ensure the security configuration management and vulnerability management are in place in your cloud security mandate. The security configuration management in cloud should include the following areas: Define the secure configuration baselines for different resource types in the cloud, such as the web portal/console, management and control plane, and resources running in the IaaS, PaaS and SaaS services. Ensure the security baselines address the risks in different control areas such as network security, identity management, privileged access, data protection and so on. Use tools to continuously measure, audit, and enforce the configuration to prevent configuration deviating from the baseline. Develop a cadence to stay updated with security features, for instance, subscribe to the service updates. Utilize a security health or compliance check mechanism (such as Secure Score, Compliance Dashboard in Microsoft Defender for Cloud) to regularly review security configuration posture and remediate the gaps identified. The vulnerability management in the cloud should include the following security aspects: Regularly assess and remediate vulnerabilities in all cloud resource types, such as cloud native services, operating systems, and application components. Use a risk-based approach to prioritize assessment and remediation. Subscribe to the relevant CSPM's security advisory notices and blogs to receive the latest security updates. Ensure the vulnerability assessment and remediation (such as schedule, scope, and techniques) meet the compliance requirements for your organization.dule, scope, and techniques) meet the regularly compliance requirements for your organization. | E6: GS-5 | F6: 4.1, 4.2 | G6: CA-1, CA-8, CM-1, CM-2, CM-6, RA-1, RA-3, RA-5, SI-1, SI-2, SI-5 | H6: 1.1, 1.2, 2.2, 6.1, 6.2, 6.5, 6.6, 11.2, 11.3, 11.5 | I6: TVM-03 | J6: 1. Is Defender for Cloud enabled at subscription/tenant level? 2. Is Secure Score monitored with remediation actions tracked? | K6: 1. Secure Score export ( az security secure-score-control list ). 2. Regulatory compliance report ( az security regulatory-compliance-standards show). | L6: 2
A7: CSF-AZ-GS-06 | B7: Define and implement identity and privileged access strategy | C7: Establish a cloud identity and privileged access approach as part of your organization’s overall security access control strategy. This strategy should include documented guidance, policy, and standards for the following aspects: Centralized identity and authentication system (such as Azure AD) and its interconnectivity with other internal and external identity systems Privileged identity and access governance (such as access request, review and approval) Privileged accounts in emergency (break-glass) situation Strong authentication (passwordless authentication and multifactor authentication) methods in different use cases and conditions. Secure access by administrative operations through web portal/console, command-line and API. For exception cases, where an enterprise system isn’t used, ensure adequate security controls are in place for identity, authentication and access management, and governed. These exceptions should be approved and periodically reviewed by the enterprise team. These exceptions are typically in cases such as: Use of a non-enterprise designated identity and authentication system, such as cloud-based third-party systems (may introduce unknown risks) Privileged users authenticated locally and/or use non-strong authentication methods | E7: GS-6 | F7: 5.6, 6.5, 6.7 | G7: AC-1, AC-2, AC-3, AC-4, AC-5, AC-6, IA-1, IA-2, IA-4, IA-5, IA-8, IA-9, SI-4 | H7: 7.1, 7.2, 7.3, 8.1, 8.2, 8.3, 8.4, 8.5, 8.6, 8.7, 8.8, A3.4 | I7: IAM-01 | J7: 1. Is Azure AD the central identity provider for all resources? 2. Is Privileged Identity Management (PIM) enabled for JIT elevation? 3. Is MFA enforced for privileged roles? | K7: 1. Directory role assignment export ( az role assignment list -- all ). 2. PIM activation logs ( Get-AzureADMSPrivilegedRoleAssignment ). 3. Conditional Access policy export ( az ad conditionalaccess policy list ). | L7: 3
A8: CSF-AZ-GS-07 | B8: Define and implement logging, threat detection and incident response strategy | C8: Establish a logging, threat detection and incident response strategy to rapidly detect and remediate threats and meet compliance requirements. Security operations (SecOps / SOC) team should prioritize high quality alerts and seamless experiences so that they can focus on threats rather than log integration and manual steps. This strategy should include documented policy, procedure and standards for the following aspects: The security operations (SecOps) organization's role and responsibilities A well-defined and regularly tested incident response plan and handling process aligning with NIST SP 800-61 (Computer Security Incident Handling Guide) or other industry frameworks. Communication and notification plan with your customers, suppliers, and public parties of interest. Simulate both expected and unexpected security events within your cloud environment to understand the effectiveness of your preparation. Iterate on the outcome of your simulation to improve the scale of your response posture, reduce time to value, and further reduce risk. Preference of using extended detection and response (XDR) capabilities, such as Azure Defender capabilities, to detect threats in various areas. Use of cloud native capability (e.g., as Microsoft Defender for Cloud) and third-party platforms for incident handling, such as logging and threat detection, forensics, and attack remediation and eradication. Prepare the necessary runbooks, both manual and automated, to ensure reliable and consistent responses. Define key scenarios (such as threat detection, incident response, and compliance) and set up log capture and retention to meet the scenario requirements. Centralized visibility of and correlation information about threats, using SIEM, native cloud threat detection capability, and other sources. Post-incident activities, such as lessons learned and evidence retention. | E8: GS-7 | F8: 8.1, 13.1, 17.2, 17.4,17.7 | G8: AU-1, IR-1, IR-2, IR-10, SI-1, SI-5 | H8: 10.1, 10.2, 10.3, 10.4, 10.5, 10.6, 10.7, 10.8, 10.9, 12.10, A3.5 | I8: LOG-01 | J8: 1. Are diagnostic logs for critical resources exported to Log Analytics or Sentinel? 2. Are Defender for Cloud alerts integrated with Sentinel for IR workflows? | K8: 1. Diagnostic settings config ( az monitor diagnostic-settings list ). 2. Sentinel connector configuration logs. 3. Defender for Cloud security alert export ( az security alert list ). | L8: 3
A9: CSF-AZ-GS-08 | B9: Define and implement backup and recovery strategy | C9: Establish a backup and recovery strategy for your organization. This strategy should include documented guidance, policy, and standards in the following aspects: Recovery time objective (RTO) and recovery point objective (RPO) definitions in accordance with your business resiliency objectives, and regulatory compliance requirements. Redundancy design (including backup, restore and replication) in your applications and infrastructure for both in cloud and on-premises. Consider regional, region-pairs, cross-regional recovery and off-site storage location as part of your strategy. Protection of backup from unauthorized access and tempering using controls such as data access control, encryption and network security. Use of backup and recovery to mitigate the risks from emerging threats, such as ransomware attacks. And also secure the backup and recovery data itself from these attacks. Monitoring the backup and recovery data and operations for audit and alerting purposes. | E9: GS-8 | F9: 11.1 | G9: CP-1, CP-9, CP-10 | H9: 3.4 | I9: BCR-09 | J9: 1. Are Azure Backup policies applied to all supported workloads? 2. Are restore tests performed periodically to validate RPO/RTO? | K9: 1. Recovery Services Vault backup policy config ( az backup policy list ). 2· Restore job logs ( az backup job list -- vault-name <vault> ). | L9: 2
A10: CSF-AZ-GS-09 | B10: Define and implement endpoint security strategy | C10: Establish a cloud endpoint security strategy which includes the following aspects:- Deploy the endpoint detection and response and anti-malware capability into your endpoint and integrate with the threat detection and SIEM solution and the security operations process. Follow the Microsoft Cloud Security Benchmark to ensure endpoint related security settings in other respective areas (such as network security, posture vulnerability management, identity and privileged access, and logging and threat detections) are also in place to provide a defense-in-depth protection for your endpoint. Prioritize the endpoint security in your production environment but ensure that non-production environments (such as test and build environment used in the DevOps process) are also secured and monitored, as these environments can also be used to introduce malware and vulnerabilities into the production environment. | E10: GS-9 | F10: 4.4, 10.1 | G10: SI-2, SI-3, SC-3 | H10: 5.1, 5.2, 5.3, 5.4, 11.5 | I10: UEM-01 | J10: 1. Are all Azure VMs onboarded to Defender for Servers (Defender for Endpoint)? 2. Is endpoint protection (anti-malware) healthy and signatures up to date? | K10: 1. Defender for Cloud endpoint protection compliance ( az security assessment list -- query "[?contains(name, 'antimalware' )]" ). 2. Device signature status ( Get-MpSignature for Windows, mdatp health for Linux). | L10: 2
A11: CSF-AZ-GS-10 | B11: Define and implement DevOps security strategy | C11: Mandate the security controls as part of the organization’s DevOps engineering and operation standard. Define the security objectives, control requirements, and tooling specifications in accordance with enterprise and cloud security standards in your organization. Encourage the use of DevOps as an essential operating model in your organization for its benefits in rapidly identifying and remediating vulnerabilities using different type of automations (such as infrastructure as code provision, and automated SAST and DAST scan) throughout the CI/CD workflow. This ‘shift left’ approach also increases visibility and ability to enforce consistent security checks in your deployment pipeline, effectively deploying security guardrails into the environment ahead of time to avoid last minute security surprises when deploying a workload into production. When shifting security controls left into the pre-deployment phases, implement security guardrails to ensure the controls are deployed and enforced throughout your DevOps process. This technology could include resource deployment templates (such as Azure ARM template) to define guardrails in the IaC (infrastructure as code), resource provisioning and audit to restrict which services or configurations can be provisioned into the environment. For the run-time security controls of your workload, follow the Microsoft Cloud Security Benchmark to design and implement effective the controls, such as identity and privileged access, network security, endpoint security, and data protection inside your workload applications and services. | E11: GS-10 | F11: 4.1, 4.2, 16.1, 16.2 | G11: SA-12, SA-15, CM-1, CM-2, CM-6, AC-2, AC-3, AC-6, SA-11, AU-6, AU-12, SI-4 | H11: 2.2, 6.1, 6.2, 6.3, 6.5, 7.1, 10.1, 10.2, 10.3, 10.6, 12.2 | I11: AIS-03 | J11: 1. Are CI/CD pipelines (Azure DevOps, GitHub) integrated with SAST/DAST scans to block insecure code? 2. Are secrets, credentials, and tokens stored in Azure Key Vault instead of source code/repos? 3. Are DevOps audit logs (pipeline events, org changes) exported to Sentinel or Log Analytics for monitoring? | K11: 1. Pipeline definitions showing CodeQL/SAST/DAST steps ( azure-pipelines.yml, GitHub Actions YAML). 2. Azure Key Vault secret inventory ( az keyvault secret list ). 3. Azure DevOps/GitHub audit log export ( az devops audit-log list , GitHub audit log API). 4. Sentinel rules/alerts monitoring DevOps activity. | L11: 4
A12: CSF-AZ-GS-11 | B12: Align organization roles, responsibilities and accountabilities | C12: Ensure a multi-cloud strategy is defined in your cloud and security governance, risk management, and operation process which should include the following aspects: Multi-cloud adoption: For organizations that operate multi-cloud infrastructure and Educate your organization to ensure teams understand the feature difference between the cloud platforms and technology stack. Build, deploy, and/or migrate solutions that are portable. Allow for ease of movement between cloud platforms with minimum vendor lock-in while utilizing cloud native features adequately for the optimal result from the cloud adoption. Cloud and security operations: Streamline security operations to support the solutions across each cloud, through a central set of governance and management processes which share common operations processes, regardless of where the solution is deployed and operated. Tooling and technology stack: Choose the appropriate tooling that supports multi-cloud environment to help with establishing unified and centralized management platforms which may include all the security domains discussed in this security benchmark. | E12: GS-11 | F12: N/A | G12: N/A | H12: N/A | I12: GRC-10 | J12: 1. Are multi-cloud connectors (AWS, GCP) enabled in Defender for Cloud for unified security posture? 2. Are policies and compliance frameworks (CIS, NIST, PCI) applied consistently across Azure, AWS, and GCP? 3. Is Secure Score or equivalent posture score tracked across clouds? | K12: 1. Multicloud connector status ( az security connector list ). 2. Compliance exports from Defender for Cloud across providers. 3. Multi-cloud Secure Score dashboard export from Defender for Cloud CSPM. | L12: 3

Sheet Sources
A2: Azure Landing | B2: https://learn.microsoft.com/en-us/assessments/8fefc6d5-97ac-42b3-8e97-d82701e55bab/sessions/976e7e9d-4efa-48b8-b493-768d4283abc7?mode=guidance&id=8fefc6d5-97ac-42b3-8e97-d82701e55bab&session=976e7e9d-4efa-48b8-b493-768d4283abc7&source=docs&tab=tab-answersummary
A3: MCSB | B3: https://learn.microsoft.com/en-us/security/benchmark/azure/mcsb-network-security
